{
  "video_id": "3LuchpUc7PU",
  "title": "Should I Buy An Elgato Game Capture??",
  "url": "https://www.youtube.com/watch?v=3LuchpUc7PU",
  "comment_count": 337,
  "comments": [
    {
      "author": "@Finn-r6d",
      "author_id": "UCfqU8X8xnmOqpOK_QoS5gRQ",
      "text": "The least viewed video\n\n\n\n\n\n\nTo everyone before me saying the same thing sorry for stealing the top",
      "likes": 259,
      "timestamp": 1734998400,
      "parent": "root",
      "is_reply": false
    },
    {
      "author": "@ihsan9616",
      "author_id": "UCtWhbWRy2CZHZIkXL9nFrpA",
      "text": "Org indo ------>",
      "likes": 19,
      "timestamp": 1703376000,
      "parent": "root",
      "is_reply": false
    },
    {
      "author": "@Littlehughman",
      "author_id": "UCffVFTcT3bMi4zzuqBpmshA",
      "text": "least seen vid that mr beast has ever made but its still amazing",
      "likes": 16,
      "timestamp": 1703376000,
      "parent": "root",
      "is_reply": false
    },
    {
      "author": "@MysticLi-19",
      "author_id": "UCsUzqksqk3HnvJAKbO9SUag",
      "text": "Found this by scrolling All the way down from “popular”",
      "likes": 13,
      "timestamp": 1703376000,
      "parent": "root",
      "is_reply": false
    },
    {
      "author": "@tommyc5930",
      "author_id": "UCDVQbTbawWEdpQQcV-wdqCQ",
      "text": "Your my favourite youtuber by far :)",
      "likes": 255,
      "timestamp": 1450915200,
      "parent": "root",
      "is_reply": false
    },
    {
      "author": "@Mrlemoa",
      "author_id": "UC78CrYuriylooQtPw7C4GKg",
      "text": "Most unpopular video but I respect it",
      "likes": 8,
      "timestamp": 1734998400,
      "parent": "root",
      "is_reply": false
    },
    {
      "author": "@SYHS-l2z",
      "author_id": "UCA0LfNpqVXWWZfE5lvUYXZQ",
      "text": "For those who scrolled all the way to the bottom in order of popularity✋",
      "likes": 4,
      "timestamp": 1763942400,
      "parent": "root",
      "is_reply": false
    },
    {
      "author": "@AJD-Israel",
      "author_id": "UC5Fbjs8PVzMPApHE8uLmzWw",
      "text": "כל הכבוד, הגעת לסוף של הפופולריות🎉",
      "likes": 2,
      "timestamp": 1763942400,
      "parent": "root",
      "is_reply": false
    },
    {
      "author": "@Splashyscarab89",
      "author_id": "UC2VdcOfL1A79b83aI6H1UXQ",
      "text": "This man has come very far im proud of you jimmy",
      "likes": 83,
      "timestamp": 1703376000,
      "parent": "root",
      "is_reply": false
    },
    {
      "author": "@Gypsyx",
      "author_id": "UC7gozbdUqpQOYN1og_d-J9g",
      "text": "Right click on clip\nProperties \nUncheck maintain aspect ratio \nThat should fix your black bars problem",
      "likes": 57,
      "timestamp": 1450915200,
      "parent": "root",
      "is_reply": false
    },
    {
      "author": "@Burnt_notfound",
      "author_id": "UCZb1LC0VkpZU7TX60wkgyaA",
      "text": "The most unpopular vid",
      "likes": 7,
      "timestamp": 1703376000,
      "parent": "root",
      "is_reply": false
    },
    {
      "author": "@Mr.Gamergato",
      "author_id": "UCLSgYjcOResIQJ7_wUDzu4Q",
      "text": "Here a legend began",
      "likes": 2,
      "timestamp": 1761264000,
      "parent": "root",
      "is_reply": false
    },
    {
      "author": "@PSE-i99u",
      "author_id": "UC6F_yvhnWbROw72LSX_XaiA",
      "text": "Least viewed mr beast video 😮",
      "likes": 6,
      "timestamp": 1734998400,
      "parent": "root",
      "is_reply": false
    },
    {
      "author": "@onstr",
      "author_id": "UCrDsKBylMLXi9L1m96KtSug",
      "text": "Now the goal is to shoot in 4K.  Can't wait to see what 5 years brings.",
      "likes": 32,
      "timestamp": 1640304000,
      "parent": "root",
      "is_reply": false
    },
    {
      "author": "@stronkbonk1",
      "author_id": "UCY5dpnRN0uadOXGq382O2Jg",
      "text": "mr beast least popular video",
      "likes": 7,
      "timestamp": 1734998400,
      "parent": "root",
      "is_reply": false
    },
    {
      "author": "@soxled1836",
      "author_id": "UCOeWYItmfuxfMCeh4_msjcw",
      "text": "I just bought one thx for the review!",
      "likes": 4,
      "timestamp": 1703376000,
      "parent": "root",
      "is_reply": false
    },
    {
      "author": "@heikep.1531",
      "author_id": "UClsdLR7SvjVhkymR26HsIgw",
      "text": "This just took me 1 Minute",
      "likes": 2,
      "timestamp": 1761264000,
      "parent": "root",
      "is_reply": false
    },
    {
      "author": "@PROUNKNOWN",
      "author_id": "UC72Lfhb5VD1pK3lMVDwJLAw",
      "text": "Anyone in 2024?",
      "likes": 128,
      "timestamp": 1734998400,
      "parent": "root",
      "is_reply": false
    },
    {
      "author": "@voidkarnage",
      "author_id": "UCm3m7A4Mlb_oSVM7r8r7rEQ",
      "text": "Thank you for the review",
      "likes": 1,
      "timestamp": 1753315200,
      "parent": "root",
      "is_reply": false
    },
    {
      "author": "@G513-e6s",
      "author_id": "UCQpHDsBTrhkgQgB0RKOwnig",
      "text": "The most unpopular vid of mrbeast",
      "likes": 3,
      "timestamp": 1734998400,
      "parent": "root",
      "is_reply": false
    },
    {
      "author": "@GoodBoyMikka",
      "author_id": "UCJvIYyPSasO_jXFEIxwZiSw",
      "text": "Nostalgia when mr.beast making low budget videos now he earning millions",
      "likes": 3,
      "timestamp": 1703376000,
      "parent": "root",
      "is_reply": false
    },
    {
      "author": "@Itzme_adubobyplayz",
      "author_id": "UCIee3A1dDTrS4YNa3MsRuUg",
      "text": "Wow the least veiwed vid",
      "likes": 8,
      "timestamp": 1671840000,
      "parent": "root",
      "is_reply": false
    },
    {
      "author": "@GoniffYT",
      "author_id": "UCC58uwDidQq-8OSUcbT-0-A",
      "text": "Primer video de mrbeast",
      "likes": 2,
      "timestamp": 1734998400,
      "parent": "root",
      "is_reply": false
    },
    {
      "author": "@coolboydaniel6627",
      "author_id": "UCxSZQkDzuL3b_RUqiFuw_kw",
      "text": "This is the least viewed vids of him and it’s still good",
      "likes": 10,
      "timestamp": 1671840000,
      "parent": "root",
      "is_reply": false
    },
    {
      "author": "@JOJOSpotlight",
      "author_id": "UCO4ebfxmnvAAEytkqew6dCQ",
      "text": "WHY YES THE ELGATO I THINK IS MUCH BETTER THAN EVERYTHING! I Hook it to a lightning adapter to record MCPE...it's pretty useful!",
      "likes": 11,
      "timestamp": 1450915200,
      "parent": "root",
      "is_reply": false
    },
    {
      "author": "@Zwarx47",
      "author_id": "UC6o3T9p4ZeP5XKAc022QPxQ",
      "text": "Yutuber baru maklum sepi",
      "likes": 6,
      "timestamp": 1703376000,
      "parent": "root",
      "is_reply": false
    },
    {
      "author": "@BilManuk",
      "author_id": "UCsdvK2zde71vEVwHqET_nsA",
      "text": "Iya ancrit sepi",
      "likes": 4,
      "timestamp": 1703376000,
      "parent": "root",
      "is_reply": false
    },
    {
      "author": "@grahamkavanagh1520",
      "author_id": "UC6mI4PFC607EFf8YIUWeqjg",
      "text": "It's almost 2023 now the biggest YouTuber in the world look where he came from and look at him now what a motivated man",
      "likes": 10,
      "timestamp": 1703376000,
      "parent": "root",
      "is_reply": false
    },
    {
      "author": "@chrisnl7354",
      "author_id": "UCWsqUQk8tF8tZ7-jV05Q4TQ",
      "text": "Thanks mr beast I didn’t expect to see a tutorial from you",
      "likes": 9,
      "timestamp": 1640304000,
      "parent": "root",
      "is_reply": false
    },
    {
      "author": "@강아미1",
      "author_id": "UCkO0KXHqYc_Fh3FjX-WJdLg",
      "text": "미스터비스트는 제일 작게 나온 조회수도 5.3만 이구나...😢",
      "likes": 2,
      "timestamp": 1737676800,
      "parent": "root",
      "is_reply": false
    },
    {
      "author": "@maggiebuilds3",
      "author_id": "UC3rF0Xw4NEi1slSMGWnuVfg",
      "text": "10 years ago today!!",
      "likes": 1,
      "timestamp": 1755993600,
      "parent": "root",
      "is_reply": false
    },
    {
      "author": "@bonafide9516",
      "author_id": "UClZS9t-ggMgwfXtCOhvpDFw",
      "text": "I can't stop watching your videos",
      "likes": 2,
      "timestamp": 1608768000,
      "parent": "root",
      "is_reply": false
    },
    {
      "author": "@Fliyx_Fan",
      "author_id": "UC4azvswmzl7wsYWXDJJMmsw",
      "text": "Lebst view Video of mr Beats",
      "likes": 3,
      "timestamp": 1734998400,
      "parent": "root",
      "is_reply": false
    },
    {
      "author": "@TR0x-socra",
      "author_id": "UCOIvUNgXj7zOZyYIis9TDpQ",
      "text": "Thanks man I’ve been seeing that bug with my elgato so I have just been using the built in ps4 capture but thanks for pointing out how to fix that",
      "likes": 2,
      "timestamp": 1703376000,
      "parent": "root",
      "is_reply": false
    },
    {
      "author": "@zonkflow",
      "author_id": "UCfJbloBt3whzjrjaggLvoWA",
      "text": "tumben sepi bang",
      "likes": 3,
      "timestamp": 1703376000,
      "parent": "root",
      "is_reply": false
    },
    {
      "author": "@monosocio71",
      "author_id": "UC5c0D7-N-l1hDVLcVdmij7g",
      "text": "No puedo creer lo lejos que llegaste amigo",
      "likes": 1,
      "timestamp": 1703376000,
      "parent": "root",
      "is_reply": false
    },
    {
      "author": "@cleyii",
      "author_id": "UCpVVuw7Pxg25dEdpJi0CkKw",
      "text": "Tumben sepi :\"",
      "likes": 4,
      "timestamp": 1703376000,
      "parent": "root",
      "is_reply": false
    },
    {
      "author": "@Somethingsomethingyes",
      "author_id": "UCUFLsvOqbxrkyN8dzeB3iyg",
      "text": "Anyone else just picked popular and scrolled all the way down",
      "likes": 6,
      "timestamp": 1703376000,
      "parent": "root",
      "is_reply": false
    },
    {
      "author": "@kstarwarsgames8895",
      "author_id": "UCYbZM9FQ4ZsyaMN8RmJwJ5g",
      "text": "Jimmy has changed",
      "likes": 2,
      "timestamp": 1671840000,
      "parent": "root",
      "is_reply": false
    },
    {
      "author": "@Avaresh1",
      "author_id": "UCQm7OcbZcwjQ1Cw6DKNAfwA",
      "text": "Wow jimmy you got 87 , 47k viewed videos that’s crazy",
      "likes": 2,
      "timestamp": 1734998400,
      "parent": "root",
      "is_reply": false
    },
    {
      "author": "@shveynaya_mozaika",
      "author_id": "UCt_d4BwsCnQsRl0C_6ASifQ",
      "text": "ЭТО ТОЛЬКО НАЧАЛО🎉🎉🎉🎉",
      "likes": 3,
      "timestamp": 1703376000,
      "parent": "root",
      "is_reply": false
    },
    {
      "author": "@catgoatfoxlover",
      "author_id": "UCgx6JXNtVzV57TZRszmeEVg",
      "text": "Watching all of his vids!",
      "likes": 1,
      "timestamp": 1640304000,
      "parent": "root",
      "is_reply": false
    },
    {
      "author": "@epepburik6636",
      "author_id": "UC-EFGfgsG3r7EzzmVHRrKhQ",
      "text": "Youtuber sepi",
      "likes": 4,
      "timestamp": 1703376000,
      "parent": "root",
      "is_reply": false
    },
    {
      "author": "@mowmi_marcin480",
      "author_id": "UC5PMAp-Mm6Ao46GGG86c6hw",
      "text": "Happy new year 2022",
      "likes": 2,
      "timestamp": 1671840000,
      "parent": "root",
      "is_reply": false
    },
    {
      "author": "@Doginthesleep",
      "author_id": "UCgWBQlGn10NoHVC0qKclnJQ",
      "text": "Isn’t rendering so fun? 😂 when I got a 4kgopro there was a lot to figure out haha finally had to learn about ram and all the things.",
      "likes": 3,
      "timestamp": 1608768000,
      "parent": "root",
      "is_reply": false
    },
    {
      "author": "@leedmstjd530",
      "author_id": "UCtQBWX9CjZOoXcSzADqwYqw",
      "text": "미스터 비스트 조회수가 5.2회 밖에 없다고? ㅋㅋㅋㅋㅋㅋ",
      "likes": 2,
      "timestamp": 1734998400,
      "parent": "root",
      "is_reply": false
    },
    {
      "author": "@THETROLL-ZONE",
      "author_id": "UCaECNn4mtb9wS7M38H86jxA",
      "text": "hello here after 9 years❤❤❤❤😊😊",
      "likes": 2,
      "timestamp": 1753315200,
      "parent": "root",
      "is_reply": false
    },
    {
      "author": "@caydengraham6635",
      "author_id": "UCIaJtP9j-CEX7miowL1NaqQ",
      "text": "Who else scrolled all the way down to find his least viewed vid? 😂",
      "likes": 6,
      "timestamp": 1671840000,
      "parent": "root",
      "is_reply": false
    },
    {
      "author": "@MoneyTimeKings",
      "author_id": "UC7PtUIwM7g81lZKEwd4vyqA",
      "text": "That elgato looks slightly sharper. With volour correct theyd both look better though, however if u got the hd60, then i say bye the inbuilt recording software",
      "likes": 8,
      "timestamp": 1450915200,
      "parent": "root",
      "is_reply": false
    },
    {
      "author": "@ElMarcusxdd",
      "author_id": "UCg9VKBJmjQ3ClEKak2J2QAw",
      "text": "Si este es el video menos visto de MrBeast.\n\nHoy rebasó a T Series en suscriptores. \n\nAhora es el canal con más suscriptores en todo el mundo 267 millones!!\n\nFelicidades Jimmy y su equipo!",
      "likes": 2,
      "timestamp": 1734998400,
      "parent": "root",
      "is_reply": false
    },
    {
      "author": "@adawg___4",
      "author_id": "UCGgMgZ6vjd-LValsdCXlh7g",
      "text": "Insane progression. Hope he got use out of the Elgato.",
      "likes": 1,
      "timestamp": 1703376000,
      "parent": "root",
      "is_reply": false
    },
    {
      "author": "@Nexusfabi_live",
      "author_id": "UCN9RSYlaY_8-zPeYW3GVCQg",
      "text": "Whos in 2023?",
      "likes": 11,
      "timestamp": 1703376000,
      "parent": "root",
      "is_reply": false
    },
    {
      "author": "@gamingkid7576",
      "author_id": "UCsaHWbsZB052-4G7WJXjL_g",
      "text": "I am trying to save up for one of these things.",
      "likes": 1,
      "timestamp": 1482537600,
      "parent": "root",
      "is_reply": false
    },
    {
      "author": "@ferraselrecio6747",
      "author_id": "UCuOyVb99DHlazn-u4d3kdUg",
      "text": "Hace 10 años lograr su meta",
      "likes": 1,
      "timestamp": 1758672000,
      "parent": "root",
      "is_reply": false
    },
    {
      "author": "@starship2023",
      "author_id": "UCRmuj9aC2vJ_1HKmGQlV3jQ",
      "text": "Mr Beast least viewed video",
      "likes": 4,
      "timestamp": 1734998400,
      "parent": "root",
      "is_reply": false
    },
    {
      "author": "@sandikurniawan0458",
      "author_id": "UCHM2YwyAynKWTNmhzuuV72g",
      "text": "Masih pemula?",
      "likes": 5,
      "timestamp": 1703376000,
      "parent": "root",
      "is_reply": false
    },
    {
      "author": "@pen8936",
      "author_id": "UC7e-oqUlk3KG-kaZ4PWdTww",
      "text": "5k hype",
      "likes": 0,
      "timestamp": 1450915200,
      "parent": "root",
      "is_reply": false
    },
    {
      "author": "@Maxuta99k",
      "author_id": "UCMt4MomeGIE-cyiwDUOluAA",
      "text": "Всем привет 👋👋👋",
      "likes": 2,
      "timestamp": 1761264000,
      "parent": "root",
      "is_reply": false
    },
    {
      "author": "@valtersoderlund3820",
      "author_id": "UCtJ0RfSiAw3omB000xCDCRg",
      "text": "holy late",
      "likes": 2,
      "timestamp": 1761264000,
      "parent": "root",
      "is_reply": false
    },
    {
      "author": "@Tomomer-y5t",
      "author_id": "UCO3AW2GUExEwhVaPCU8fCQQ",
      "text": "Jimmy i'm so proud of you have come so far.",
      "likes": 10,
      "timestamp": 1703376000,
      "parent": "root",
      "is_reply": false
    },
    {
      "author": "@hvelez4646",
      "author_id": "UCo83Olss6d5uRyyMKEkctVg",
      "text": "yoooooooooooo throwback",
      "likes": 0,
      "timestamp": 1671840000,
      "parent": "root",
      "is_reply": false
    },
    {
      "author": "@Girlbyeno",
      "author_id": "UC28vcAjwJYnSNDr9H8AwNgg",
      "text": "Wow you growing really fast!",
      "likes": 0,
      "timestamp": 1671840000,
      "parent": "root",
      "is_reply": false
    },
    {
      "author": "@PenguinMasterYT",
      "author_id": "UCcUyFKT2D0uOTSyrtzx5feA",
      "text": "Just went most popular and went to the bottom to find this bad boy",
      "likes": 2,
      "timestamp": 1671840000,
      "parent": "root",
      "is_reply": false
    },
    {
      "author": "@zuldhiya",
      "author_id": "UCe-nrtyr4W60SjClKoJlb0w",
      "text": "Ninggalin jejak",
      "likes": 2,
      "timestamp": 1703376000,
      "parent": "root",
      "is_reply": false
    },
    {
      "author": "@qianjayapratomo9313",
      "author_id": "UCCv9tS50N1CtlAiefeHQvjg",
      "text": "Sepi amat bang",
      "likes": 4,
      "timestamp": 1703376000,
      "parent": "root",
      "is_reply": false
    },
    {
      "author": "@catbackstohatchbacks7566",
      "author_id": "UCzPebdfcuvkTYHjRvTyC4mQ",
      "text": "What’s up. I really need one of those",
      "likes": 0,
      "timestamp": 1577145600,
      "parent": "root",
      "is_reply": false
    },
    {
      "author": "@한빈-k2n",
      "author_id": "UCUcrW3VtaFcodDYiRsJcGDA",
      "text": "미스터비스트 너가 나에게 서울아파트를 절대로 사줄수 없을거야 그건 나의 능혁 밖에있어",
      "likes": 2,
      "timestamp": 1737676800,
      "parent": "root",
      "is_reply": false
    },
    {
      "author": "@oskalol132",
      "author_id": "UCHGz19lgDZad1InqRXUsF9g",
      "text": "17k views!!?!???",
      "likes": 3,
      "timestamp": 1671840000,
      "parent": "root",
      "is_reply": false
    },
    {
      "author": "@LUKZ_LUCKY",
      "author_id": "UCFfSt6dK8lwKtDlLqp4QPUg",
      "text": "You re my favorite youtubers",
      "likes": 1,
      "timestamp": 1703376000,
      "parent": "root",
      "is_reply": false
    },
    {
      "author": "@trash8676",
      "author_id": "UCGWfCfZUguK4x3xWfwE5Fvg",
      "text": "pretty goood",
      "likes": 1,
      "timestamp": 1608768000,
      "parent": "root",
      "is_reply": false
    },
    {
      "author": "@GoniffYT",
      "author_id": "UCC58uwDidQq-8OSUcbT-0-A",
      "text": "Menos visto",
      "likes": 2,
      "timestamp": 1734998400,
      "parent": "root",
      "is_reply": false
    },
    {
      "author": "@LuisHernandez-pt7xw",
      "author_id": "UCziDekzGDmOqiPC4HbI80rw",
      "text": "Wow this the least popular videa 😢",
      "likes": 3,
      "timestamp": 1703376000,
      "parent": "root",
      "is_reply": false
    },
    {
      "author": "@EugenioSorianio",
      "author_id": "UCLBdc265wCX-2PIQjTVMfNg",
      "text": "Right here",
      "likes": 1,
      "timestamp": 1734998400,
      "parent": "root",
      "is_reply": false
    },
    {
      "author": "@NiceHyper01",
      "author_id": "UCNx0nXIXfLb1A-hf7JHFYUw",
      "text": "okie dokie",
      "likes": 0,
      "timestamp": 1703376000,
      "parent": "root",
      "is_reply": false
    },
    {
      "author": "@Caktuso",
      "author_id": "UCAjfX2MqZcxX3z2YW66aurw",
      "text": "bro now did billions of views",
      "likes": 1,
      "timestamp": 1703376000,
      "parent": "root",
      "is_reply": false
    },
    {
      "author": "@analuizasamello",
      "author_id": "UCFMAjDmgaPat6TGy8mUF3eg",
      "text": "Here until this vid becomes popular rn its at 19k",
      "likes": 1,
      "timestamp": 1671840000,
      "parent": "root",
      "is_reply": false
    },
    {
      "author": "@baselvmt5417",
      "author_id": "UCjxnDNB2qkPKoV5802e8b4Q",
      "text": "i don't havve money to buy elgato rn i'll try to get it next month thank you!~!",
      "likes": 1,
      "timestamp": 1734998400,
      "parent": "root",
      "is_reply": false
    },
    {
      "author": "@benonsen",
      "author_id": "UCfVA2s7E-3xdRezu1hYJtmw",
      "text": "Wonder if hes still using his ps4 right about now LOL",
      "likes": 1,
      "timestamp": 1640304000,
      "parent": "root",
      "is_reply": false
    },
    {
      "author": "@B16FFNOOB",
      "author_id": "UCUgyax3WKo5T_nveltIk8rQ",
      "text": "only 51k ????!!!!!!!!!!!",
      "likes": 4,
      "timestamp": 1734998400,
      "parent": "root",
      "is_reply": false
    },
    {
      "author": "@aaronsgamingchannelandrevi6782",
      "author_id": "UCmRSSStVxNC0cBueatT_-QA",
      "text": "Mr Beast Gaming at its finest",
      "likes": 1,
      "timestamp": 1608768000,
      "parent": "root",
      "is_reply": false
    },
    {
      "author": "@jethalalgada3358",
      "author_id": "UCREwwDKJqGIrndZal4b26WA",
      "text": "Damn",
      "likes": 1,
      "timestamp": 1671840000,
      "parent": "root",
      "is_reply": false
    },
    {
      "author": "@Ger_1089",
      "author_id": "UCEF3_qVqzMXKvXkB8HSGQhg",
      "text": "🙏🙏",
      "likes": 0,
      "timestamp": 1671840000,
      "parent": "root",
      "is_reply": false
    },
    {
      "author": "@salttydawg2273",
      "author_id": "UC_27NbIWLwa16EAktSnARkw",
      "text": "What have I found????? Wow... this is crazy!!!!!",
      "likes": 0,
      "timestamp": 1640304000,
      "parent": "root",
      "is_reply": false
    },
    {
      "author": "@Davidemosaurus",
      "author_id": "UCpZVpkb2s20EqdirMKXPDLw",
      "text": "3 mil.subs remainder.I got my elgato hd 60s but my laptop is crap.have fun",
      "likes": 1,
      "timestamp": 1545609600,
      "parent": "root",
      "is_reply": false
    },
    {
      "author": "@Ryouta0210",
      "author_id": "UCbJ7uskgSKuR2RIitOFJwDA",
      "text": "普通のYouTuberでも取れる再生数です",
      "likes": 2,
      "timestamp": 1734998400,
      "parent": "root",
      "is_reply": false
    },
    {
      "author": "@MaksimSaikin",
      "author_id": "UCrX7IINPPT85hanGokg0gVw",
      "text": "This is beautiful",
      "likes": 0,
      "timestamp": 1703376000,
      "parent": "root",
      "is_reply": false
    },
    {
      "author": "@andresguerra5970",
      "author_id": "UCNPMAT-UfLb78kzkTn1BaJw",
      "text": "Yup, you should. Greetings from Bolivia!",
      "likes": 0,
      "timestamp": 1703376000,
      "parent": "root",
      "is_reply": false
    },
    {
      "author": "@N1vkk",
      "author_id": "UC5mqLb47kkrI0syR5clKgtA",
      "text": "Imagine watching this 6 years ago",
      "likes": 0,
      "timestamp": 1671840000,
      "parent": "root",
      "is_reply": false
    },
    {
      "author": "@scaredy5975",
      "author_id": "UCpsjd_wDFKhajZleugUUclg",
      "text": "USE IT",
      "likes": 1,
      "timestamp": 1450915200,
      "parent": "root",
      "is_reply": false
    },
    {
      "author": "@ROMELGUN",
      "author_id": "UCbI3468SjNPYsOmBEEdoUHQ",
      "text": "My mission is to comment every videos on your channel....🍗🍗🍗🍗✔️✔️✔️",
      "likes": 2,
      "timestamp": 1671840000,
      "parent": "root",
      "is_reply": false
    },
    {
      "author": "@omomoh1",
      "author_id": "UC4f4alXtn7HgC5y-3BXDmOA",
      "text": "Cool",
      "likes": 0,
      "timestamp": 1671840000,
      "parent": "root",
      "is_reply": false
    },
    {
      "author": "@raisazra2720",
      "author_id": "UCfxl6It2M4rHkLmPiuAGqoA",
      "text": "Great",
      "likes": 0,
      "timestamp": 1703376000,
      "parent": "root",
      "is_reply": false
    },
    {
      "author": "@keithroyalty5323",
      "author_id": "UCDUlU_Cjz35X1EdScS-h_4g",
      "text": "❤️‍🔥",
      "likes": 2,
      "timestamp": 1671840000,
      "parent": "root",
      "is_reply": false
    },
    {
      "author": "@エレキング-s3f",
      "author_id": "UCwDNOg249j3ADlTn2ZXLf6A",
      "text": "great",
      "likes": 0,
      "timestamp": 1671840000,
      "parent": "root",
      "is_reply": false
    },
    {
      "author": "@1ALIX",
      "author_id": "UCTHiBYfmeN_XyLQBtnRx8vQ",
      "text": "YES, AND I WANT ONE!",
      "likes": 0,
      "timestamp": 1671840000,
      "parent": "root",
      "is_reply": false
    },
    {
      "author": "@ElMesModernChannelTV",
      "author_id": "UCBWS06GJG_kKnrbqJqZGeUA",
      "text": "Ooh yess found the next \"WHATS UP GUYS\"",
      "likes": 0,
      "timestamp": 1577145600,
      "parent": "root",
      "is_reply": false
    },
    {
      "author": "@AloneGamerxD1",
      "author_id": "UCzgmup7cl1gmVsBxp9FI4mw",
      "text": "Love you",
      "likes": 0,
      "timestamp": 1703376000,
      "parent": "root",
      "is_reply": false
    },
    {
      "author": "@sofiane-69130",
      "author_id": "UCpG3xLDSSe8K53_T5MKEUmQ",
      "text": "the legend was born",
      "likes": 0,
      "timestamp": 1671840000,
      "parent": "root",
      "is_reply": false
    },
    {
      "author": "@techow",
      "author_id": "UCIWVXHJyW38V2LsUKVdlePw",
      "text": "Yeah, I think you should buy it",
      "likes": 1,
      "timestamp": 1703376000,
      "parent": "root",
      "is_reply": false
    },
    {
      "author": "@spo1284",
      "author_id": "UCeZFqkmd1e9MyG8byePRK2Q",
      "text": "👍",
      "likes": 0,
      "timestamp": 1640304000,
      "parent": "root",
      "is_reply": false
    },
    {
      "author": "@rickytheman888",
      "author_id": "UCPob3F09ZxEVcu7DkNpmkUw",
      "text": "#Wankbank  keep what you have, your gameplay is just fine ",
      "likes": 1,
      "timestamp": 1450915200,
      "parent": "root",
      "is_reply": false
    },
    {
      "author": "@jovian-393",
      "author_id": "UCNQoFu1n6tXhCJcUiuxJKIQ",
      "text": "Kok sepi😂",
      "likes": 2,
      "timestamp": 1703376000,
      "parent": "root",
      "is_reply": false
    },
    {
      "author": "@sammaldonado8301",
      "author_id": "UCKxXR_SKUtos2LEupy4lZag",
      "text": "Mister beat",
      "likes": 1,
      "timestamp": 1753315200,
      "parent": "root",
      "is_reply": false
    },
    {
      "author": "@LilGurtFr",
      "author_id": "UCvUU7swROVgT79sErQpJJ_g",
      "text": "People who actually watched the video",
      "likes": 4,
      "timestamp": 1750723200,
      "parent": "root",
      "is_reply": false
    },
    {
      "author": "@artisticoliver4235",
      "author_id": "UCfeMNBPHM8QLXdrSdI0mP_A",
      "text": "Fuego",
      "likes": 1,
      "timestamp": 1703376000,
      "parent": "root",
      "is_reply": false
    },
    {
      "author": "@devinreyes9682",
      "author_id": "UCnTWbfjpsxgQLsgWk_c-qtw",
      "text": "Cool to see Jimmy before the 160M",
      "likes": 0,
      "timestamp": 1703376000,
      "parent": "root",
      "is_reply": false
    },
    {
      "author": "@connorbetancourt5605",
      "author_id": "UCdLHSINk7ova9lsWtUojgUw",
      "text": "I can't believe this how does one of your videos have under 200 comments",
      "likes": 2,
      "timestamp": 1671840000,
      "parent": "root",
      "is_reply": false
    },
    {
      "author": "@florinradulescu6034",
      "author_id": "UCho_x1yX7atGzheirctdDHw",
      "text": "O.M.G 7 august is my birthday",
      "likes": 1,
      "timestamp": 1671840000,
      "parent": "root",
      "is_reply": false
    },
    {
      "author": "@MKTubevideos",
      "author_id": "UCU4XRolFSgpU9q0BPNRDvSg",
      "text": "ElGatooooo😭😭😭😭😭",
      "likes": 1,
      "timestamp": 1671840000,
      "parent": "root",
      "is_reply": false
    },
    {
      "author": "@zigaevfixed",
      "author_id": "UCj17bsPVGQqEaMQbdFxAvcQ",
      "text": "И никто это не пересмотрел?",
      "likes": 1,
      "timestamp": 1745452800,
      "parent": "root",
      "is_reply": false
    },
    {
      "author": "@Kingmirbydraws",
      "author_id": "UCDGJ71gxQDCcNQ67q8_MKvA",
      "text": "Which el gato",
      "likes": 1,
      "timestamp": 1703376000,
      "parent": "root",
      "is_reply": false
    },
    {
      "author": "@Una_Tortuga",
      "author_id": "UCVoyWqHJZ4o8rsvy5Wb9f5w",
      "text": "Hello!",
      "likes": 2,
      "timestamp": 1734998400,
      "parent": "root",
      "is_reply": false
    },
    {
      "author": "@kev4the537",
      "author_id": "UCpk3R2pLCbFysR9uk7K4lGA",
      "text": "48k views rn",
      "likes": 1,
      "timestamp": 1734998400,
      "parent": "root",
      "is_reply": false
    },
    {
      "author": "@dolbanchik",
      "author_id": "UC5Iao3qGYqDdj_HbSOhhduQ",
      "text": "Самое не популярное видео MR BEAST набрало 30к просмотров",
      "likes": 3,
      "timestamp": 1703376000,
      "parent": "root",
      "is_reply": false
    },
    {
      "author": "@エレキング-s3f",
      "author_id": "UCwDNOg249j3ADlTn2ZXLf6A",
      "text": "good👍",
      "likes": 0,
      "timestamp": 1671840000,
      "parent": "root",
      "is_reply": false
    },
    {
      "author": "@debruuuh3504",
      "author_id": "UC37bmIHY7jZWqHP5tRh1Ang",
      "text": "Day 5, episode 274 of Mr. Beast binge watch hihi ♡",
      "likes": 1,
      "timestamp": 1640304000,
      "parent": "root",
      "is_reply": false
    },
    {
      "author": "@SnaccableShorts",
      "author_id": "UCwWVEAmFSAB1zZfc3Ilimaw",
      "text": "nice",
      "likes": 1,
      "timestamp": 1758672000,
      "parent": "root",
      "is_reply": false
    },
    {
      "author": "@atom1780",
      "author_id": "UCME_c2Ezt7O1eoTJBJZ91Mg",
      "text": "Holy 26K views",
      "likes": 1,
      "timestamp": 1703376000,
      "parent": "root",
      "is_reply": false
    },
    {
      "author": "@ardak1059",
      "author_id": "UCDjrfpaoFhjVq4Ik9yTeEvQ",
      "text": "34K",
      "likes": 1,
      "timestamp": 1703376000,
      "parent": "root",
      "is_reply": false
    },
    {
      "author": "@jonrd9214",
      "author_id": "UCIbVJUqUJNMwzWFE0Y-gBTQ",
      "text": "Does it work on any laptop?",
      "likes": 1,
      "timestamp": 1514073600,
      "parent": "root",
      "is_reply": false
    },
    {
      "author": "@kaede-chan3124",
      "author_id": "UCOJEirHlQAuy8Pql_YVOO-g",
      "text": "I come from the videos above and I set myself the challenge of seeing all but ALL of your videos",
      "likes": 0,
      "timestamp": 1703376000,
      "parent": "root",
      "is_reply": false
    },
    {
      "author": "@desihoff",
      "author_id": "UCN3m8f02Sd68XRnVUjj4JaQ",
      "text": "Yes. Yes you should buy it.",
      "likes": 1,
      "timestamp": 1671840000,
      "parent": "root",
      "is_reply": false
    },
    {
      "author": "@SunitiSingh-n2i",
      "author_id": "UCpiNYiY_kNvMIZxGxOpcCzw",
      "text": "Hlo jimmy",
      "likes": 2,
      "timestamp": 1734998400,
      "parent": "root",
      "is_reply": false
    },
    {
      "author": "@Jixty",
      "author_id": "UC-GWkU7rNsDN9u6uU_mXGgA",
      "text": "Little did you know you would be the worlds biggest youtuber",
      "likes": 0,
      "timestamp": 1671840000,
      "parent": "root",
      "is_reply": false
    },
    {
      "author": "@VKFUNDS-x3j",
      "author_id": "UCdm7XDkUQUdJah-ZXeDwPaw",
      "text": "👍👍👍👍👍👍👍👍👍",
      "likes": 0,
      "timestamp": 1734998400,
      "parent": "root",
      "is_reply": false
    },
    {
      "author": "@BraedenMartin",
      "author_id": "UCLQ5K-rmUvJPDqfqWTKUaRg",
      "text": "Yessir",
      "likes": 0,
      "timestamp": 1577145600,
      "parent": "root",
      "is_reply": false
    },
    {
      "author": "@Almonboy",
      "author_id": "UCIVcg3DFgmCgN4LG8e9HAUA",
      "text": "Halo jimyy",
      "likes": 0,
      "timestamp": 1703376000,
      "parent": "root",
      "is_reply": false
    },
    {
      "author": "@MayankAnand-b4w",
      "author_id": "UC_2S1kGkxLfF9N31E10VCIw",
      "text": "😮❤",
      "likes": 0,
      "timestamp": 1703376000,
      "parent": "root",
      "is_reply": false
    },
    {
      "author": "@kiwkiw869",
      "author_id": "UCY_t9LEN_Asbvl6_dvcV30A",
      "text": "view mr beast yg terkecil😭",
      "likes": 1,
      "timestamp": 1703376000,
      "parent": "root",
      "is_reply": false
    },
    {
      "author": "@sammaldonado8301",
      "author_id": "UCKxXR_SKUtos2LEupy4lZag",
      "text": "Mister beast",
      "likes": 1,
      "timestamp": 1753315200,
      "parent": "root",
      "is_reply": false
    },
    {
      "author": "@SuperSathya-b9s",
      "author_id": "UCG98K29XiGBDqtvfFvkEIEw",
      "text": "Oo",
      "likes": 1,
      "timestamp": 1703376000,
      "parent": "root",
      "is_reply": false
    },
    {
      "author": "@pesosreal",
      "author_id": "UCHr47dhjAMRFYE0J1sUUzgg",
      "text": "Yes",
      "likes": 1,
      "timestamp": 1703376000,
      "parent": "root",
      "is_reply": false
    },
    {
      "author": "@The67Bois",
      "author_id": "UCFrgKdBx_vE4HAfa-OhjK3Q",
      "text": "Least viewed but more than my whole channel",
      "likes": 1,
      "timestamp": 1671840000,
      "parent": "root",
      "is_reply": false
    },
    {
      "author": "@RandytheRedneck",
      "author_id": "UCdUbQFtkjhO7w7lPM_owpdg",
      "text": "😀😀",
      "likes": 1,
      "timestamp": 1671840000,
      "parent": "root",
      "is_reply": false
    },
    {
      "author": "@nyftyy",
      "author_id": "UCs6_bHXdprhM00elEm9PCFQ",
      "text": "MrBeast has a Delgato???!!!!",
      "likes": 1,
      "timestamp": 1577145600,
      "parent": "root",
      "is_reply": false
    },
    {
      "author": "@eddy2506",
      "author_id": "UCypU88ax2kYJZaRrU4aKyIg",
      "text": "GGs in the chat",
      "likes": 0,
      "timestamp": 1608768000,
      "parent": "root",
      "is_reply": false
    },
    {
      "author": "@TFKfreedom",
      "author_id": "UCFzGDi4fdFHjKGd6i66k8eg",
      "text": "😢",
      "likes": 1,
      "timestamp": 1703376000,
      "parent": "root",
      "is_reply": false
    },
    {
      "author": "@pahuillebed5189",
      "author_id": "UCuArSlYw07ujuUkYw60oSSw",
      "text": "heyyy",
      "likes": 1,
      "timestamp": 1734998400,
      "parent": "root",
      "is_reply": false
    },
    {
      "author": "@SG_GAMERxd",
      "author_id": "UCI11tYjgnZ_dhtN6S8_dQXQ",
      "text": "uh oh",
      "likes": 0,
      "timestamp": 1734998400,
      "parent": "root",
      "is_reply": false
    },
    {
      "author": "@OliverSjöberg-c9h",
      "author_id": "UCH1splhm7HM3a-UHYFbUpGQ",
      "text": "Least viewed video",
      "likes": 2,
      "timestamp": 1763942400,
      "parent": "root",
      "is_reply": false
    },
    {
      "author": "@AidanGrimes.1",
      "author_id": "UCSibauMBnp66MjWwgL9FmYw",
      "text": "Found it",
      "likes": 1,
      "timestamp": 1671840000,
      "parent": "root",
      "is_reply": false
    },
    {
      "author": "@DAXPLAYZY",
      "author_id": "UClnsPji4SZFMx7ZHgbuMa-Q",
      "text": "Yo",
      "likes": 1,
      "timestamp": 1734998400,
      "parent": "root",
      "is_reply": false
    },
    {
      "author": "@edwinhernandez7056",
      "author_id": "UCe2Al_u9drvRZBwSPLwtdiQ",
      "text": "Watching all OF MrBeast's videos until he puts me in one..",
      "likes": 1,
      "timestamp": 1640304000,
      "parent": "root",
      "is_reply": false
    },
    {
      "author": "@kekura1313",
      "author_id": "UCcFWmjF85JDBxqqQShkDkVA",
      "text": "Wow",
      "likes": 0,
      "timestamp": 1703376000,
      "parent": "root",
      "is_reply": false
    },
    {
      "author": "@unpendejop486",
      "author_id": "UCLWYRzR9nsWFUSEuk7wY4YQ",
      "text": "Español?",
      "likes": 1,
      "timestamp": 1671840000,
      "parent": "root",
      "is_reply": false
    },
    {
      "author": "@factuality65",
      "author_id": "UCuxGjLesy4TXcOcXrlGrE1w",
      "text": "Give me some challenge",
      "likes": 0,
      "timestamp": 1640304000,
      "parent": "root",
      "is_reply": false
    },
    {
      "author": "@theodore7068",
      "author_id": "UCwpedI7cu-cYLxAYBlEpM3g",
      "text": "Sepi banget om buas",
      "likes": 2,
      "timestamp": 1703376000,
      "parent": "root",
      "is_reply": false
    },
    {
      "author": "@Simjim_32",
      "author_id": "UCYj82whp2Qryndp_hXgIqBQ",
      "text": "Isn’t that insane?!",
      "likes": 1,
      "timestamp": 1748044800,
      "parent": "root",
      "is_reply": false
    },
    {
      "author": "@RealRayzi",
      "author_id": "UC2xPQunbNdY8Q9jL3VKrDbA",
      "text": "w beast best",
      "likes": 1,
      "timestamp": 1734998400,
      "parent": "root",
      "is_reply": false
    },
    {
      "author": "@fahriputra.",
      "author_id": "UCO05n092a5tZbxVzmjQa8Dg",
      "text": "Keren",
      "likes": 0,
      "timestamp": 1703376000,
      "parent": "root",
      "is_reply": false
    },
    {
      "author": "@bogotandos",
      "author_id": "UCxSuSJ-g3kT9LMWUzwwE6VA",
      "text": "Me ragala un pasaje de Bogota a New York",
      "likes": 0,
      "timestamp": 1703376000,
      "parent": "root",
      "is_reply": false
    },
    {
      "author": "@centlihankdennis2378",
      "author_id": "UCKSLSfU_wjn0__95lMc0brw",
      "text": "Hi Mrbeast num303",
      "likes": 0,
      "timestamp": 1608768000,
      "parent": "root",
      "is_reply": false
    },
    {
      "author": "@jorgzy6504",
      "author_id": "UC9qOzQaxTMPiYJGpCllqcFA",
      "text": "Wow only 20k views????",
      "likes": 0,
      "timestamp": 1671840000,
      "parent": "root",
      "is_reply": false
    },
    {
      "author": "@pranoy_rajesh",
      "author_id": "UCzwmWq0wNoioyG0VYDGOHpQ",
      "text": "i love you",
      "likes": 0,
      "timestamp": 1671840000,
      "parent": "root",
      "is_reply": false
    },
    {
      "author": "@alvar-endriadamson3724",
      "author_id": "UCY1loHw0AvNHVKn2pKSoAVg",
      "text": "damn his voice",
      "likes": 0,
      "timestamp": 1703376000,
      "parent": "root",
      "is_reply": false
    },
    {
      "author": "@Ilham-ek4ej",
      "author_id": "UC9NZQ_A0a3dWcVLA48EGRSA",
      "text": "Yo jimmy",
      "likes": 0,
      "timestamp": 1703376000,
      "parent": "root",
      "is_reply": false
    },
    {
      "author": "@sholargentleman",
      "author_id": "UCVLBUxGBG4xnnV34Ig8Zw2g",
      "text": "Thats crazy im one of the only 47k people to only see this video and thats crazy for mr beast",
      "likes": 1,
      "timestamp": 1734998400,
      "parent": "root",
      "is_reply": false
    },
    {
      "author": "@mirror7321",
      "author_id": "UCZV4qPVe-2gzSrZfqZj-sVA",
      "text": "Im in 2022)",
      "likes": 1,
      "timestamp": 1671840000,
      "parent": "root",
      "is_reply": false
    },
    {
      "author": "@Crafuzz",
      "author_id": "UCdvsLCRpxFUNrj4RJE3a6Hg",
      "text": "oke",
      "likes": 0,
      "timestamp": 1671840000,
      "parent": "root",
      "is_reply": false
    },
    {
      "author": "@jackoisntdeadanymore",
      "author_id": "UCO3HtW_HyulxV2-UnySfpww",
      "text": "Jazzism",
      "likes": 1,
      "timestamp": 1640304000,
      "parent": "root",
      "is_reply": false
    },
    {
      "author": "@NecXHD",
      "author_id": "UCtvf_M2qG2oSI7OzZOP70QQ",
      "text": "Ig you must",
      "likes": 0,
      "timestamp": 1703376000,
      "parent": "root",
      "is_reply": false
    },
    {
      "author": "@andreys6968",
      "author_id": "UC2w2lM1rW_GbsTpUTcCK7PQ",
      "text": "😅",
      "likes": 0,
      "timestamp": 1671840000,
      "parent": "root",
      "is_reply": false
    },
    {
      "author": "@ssingsingssing",
      "author_id": "UCNJLokdp2mT-uyZ3KMPitfA",
      "text": "WhyM",
      "likes": 1,
      "timestamp": 1748044800,
      "parent": "root",
      "is_reply": false
    },
    {
      "author": "@abodasaeid6077",
      "author_id": "UC5MSo-Tq6d0Fx4R-vFwYNIQ",
      "text": "👀👀",
      "likes": 0,
      "timestamp": 1671840000,
      "parent": "root",
      "is_reply": false
    },
    {
      "author": "@markofelvin",
      "author_id": "UCFjWZ7bOYH-4X9E6J8J49pg",
      "text": "yes",
      "likes": 0,
      "timestamp": 1671840000,
      "parent": "root",
      "is_reply": false
    },
    {
      "author": "@Shepiock",
      "author_id": "UCN0ZCHF2dD-E_yVY1K4Q1UQ",
      "text": "Yes you should",
      "likes": 0,
      "timestamp": 1703376000,
      "parent": "root",
      "is_reply": false
    },
    {
      "author": "@monicaoetken2658",
      "author_id": "UCoWduTsTKnEYnqQ0s-lUCBg",
      "text": "I am watching this in the time when he has 35.3 MILLION subs keep up the good work",
      "likes": 1,
      "timestamp": 1608768000,
      "parent": "root",
      "is_reply": false
    },
    {
      "author": "@amdaniaman3245",
      "author_id": "UC3BDedUplOtJUCrZhF4YPvA",
      "text": "Lowest views on Mr beast channel",
      "likes": 3,
      "timestamp": 1671840000,
      "parent": "root",
      "is_reply": false
    },
    {
      "author": "@EduCaal",
      "author_id": "UCb4JJaK0d5GEHBhvAEFpDvg",
      "text": "I want to play chess with you",
      "likes": 0,
      "timestamp": 1703376000,
      "parent": "root",
      "is_reply": false
    },
    {
      "author": "@mateus63046",
      "author_id": "UCNzJF77MV5mqS0drI8n9Hyg",
      "text": "Hehehe",
      "likes": 1,
      "timestamp": 1755993600,
      "parent": "root",
      "is_reply": false
    },
    {
      "author": "@recessed1",
      "author_id": "UCGwtJOSaWEj0raJSFNvDixA",
      "text": "Актив мясо",
      "likes": 1,
      "timestamp": 1703376000,
      "parent": "root",
      "is_reply": false
    },
    {
      "author": "@MyKaktusWorld",
      "author_id": "UCOT8-zi7jU4yFjGkZV82H7w",
      "text": "Для тех кто сможет кто прочесть я скажу: \n\n\n\n\n\n\n\n\n\n\n\n\n\n\n\n\n\n\n\n\n\n\n\n\n\n\n\nИы зачем листал до самого непопулярного видео а потом этот комментарий?",
      "likes": 4,
      "timestamp": 1734998400,
      "parent": "root",
      "is_reply": false
    },
    {
      "author": "@NisaDurmus-mb8hf",
      "author_id": "UCKVNrlRHBomLYCZ01TNXZSA",
      "text": "Yek turk",
      "likes": 2,
      "timestamp": 1703376000,
      "parent": "root",
      "is_reply": false
    },
    {
      "author": "@y2kona",
      "author_id": "UCcuJ35fETrpHn3c6ydT2-RA",
      "text": "Me beast",
      "likes": 1,
      "timestamp": 1545609600,
      "parent": "root",
      "is_reply": false
    },
    {
      "author": "@OfficialPlutoVR",
      "author_id": "UC6StBYCkQa730a8lE2M2SHA",
      "text": "Here before 20k",
      "likes": 1,
      "timestamp": 1671840000,
      "parent": "root",
      "is_reply": false
    },
    {
      "author": "@sly2sal298",
      "author_id": "UCYgzVc7ENo9SjN55dJ73e-g",
      "text": "Hmmm",
      "likes": 0,
      "timestamp": 1640304000,
      "parent": "root",
      "is_reply": false
    },
    {
      "author": "@tomphilou",
      "author_id": "UCWsXIraD_aq3A5k1Q93TbXg",
      "text": "mdr jte vois",
      "likes": 0,
      "timestamp": 1703376000,
      "parent": "root",
      "is_reply": false
    },
    {
      "author": "@randomcontentwhatido2097",
      "author_id": "UCKcGJW41I-TnCXkeZUKx5Aw",
      "text": "21k views to 200m views wow",
      "likes": 2,
      "timestamp": 1671840000,
      "parent": "root",
      "is_reply": false
    },
    {
      "author": "@angelmarianochimalcazares171",
      "author_id": "UCeWZUr2klwufoq1gKi3mVxQ",
      "text": "Omg",
      "likes": 1,
      "timestamp": 1703376000,
      "parent": "root",
      "is_reply": false
    },
    {
      "author": "@namanzly2",
      "author_id": "UCrmyxdPaw0NmSarnm3CpdcA",
      "text": "Ehh?",
      "likes": 1,
      "timestamp": 1750723200,
      "parent": "root",
      "is_reply": false
    },
    {
      "author": "@pieter3096",
      "author_id": "UCK3S1HkXZEG6oERLGAM9u1g",
      "text": "399th almost 400 :)",
      "likes": 0,
      "timestamp": 1671840000,
      "parent": "root",
      "is_reply": false
    },
    {
      "author": "@heyitsmarcelo5705",
      "author_id": "UCKYMnpl4cMPIfQOF5DBfZbQ",
      "text": "These are really great looking and will definitely boost your channel",
      "likes": 7,
      "timestamp": 1608768000,
      "parent": "root",
      "is_reply": false
    },
    {
      "author": "@carcat3654",
      "author_id": "UCiCmI0xDNZPY_DkyDkgZMrw",
      "text": "This guy is going to be famous",
      "likes": 1,
      "timestamp": 1671840000,
      "parent": "root",
      "is_reply": false
    },
    {
      "author": "@MrUn4givenswag",
      "author_id": "UCpWrB1jiQSuf4uWqJ81r5tA",
      "text": "You can also live stream MUCH better ",
      "likes": 1,
      "timestamp": 1450915200,
      "parent": "root",
      "is_reply": false
    },
    {
      "author": "@Droxcs2",
      "author_id": "UClDCwZ4Yz1W5I2zzl05XipQ",
      "text": "the least viewed video from mr beast",
      "likes": 2,
      "timestamp": 1734998400,
      "parent": "root",
      "is_reply": false
    },
    {
      "author": "@coltonchasefishing",
      "author_id": "UCAwPQDTDPSsxOAF1799OfOA",
      "text": "197th comment with 19k views",
      "likes": 2,
      "timestamp": 1671840000,
      "parent": "root",
      "is_reply": false
    },
    {
      "author": "@KCbarrelracing18",
      "author_id": "UCrZaKoCdEAV4avby5jy6-Mg",
      "text": "Is it normal to think that it’s the cat? 😭",
      "likes": 1,
      "timestamp": 1671840000,
      "parent": "root",
      "is_reply": false
    },
    {
      "author": "@ItzS1m0",
      "author_id": "UCdKr-rZii4Dl8Ny3pi5cdAw",
      "text": "Mosg unpopular video",
      "likes": 2,
      "timestamp": 1753315200,
      "parent": "root",
      "is_reply": false
    },
    {
      "author": "@wolkren2019",
      "author_id": "UCE3sEB0i0q8iHj9kZaHO4zw",
      "text": "I LOVE youu (TURKEY)",
      "likes": 0,
      "timestamp": 1671840000,
      "parent": "root",
      "is_reply": false
    },
    {
      "author": "@KingBro-k3s",
      "author_id": "UCo-he6AbJHjVQiA06Z3-ioA",
      "text": "🎉🎉🎉🎉🎉",
      "likes": 1,
      "timestamp": 1755993600,
      "parent": "root",
      "is_reply": false
    },
    {
      "author": "@OS3Richie",
      "author_id": "UC6M8MU6Ed9lfHMQyMdBK3tQ",
      "text": "Help me mrbeast I wanna make yt vids but I’m so confused with this elgato",
      "likes": 0,
      "timestamp": 1640304000,
      "parent": "root",
      "is_reply": false
    },
    {
      "author": "@Ronaldo_suii0769",
      "author_id": "UCsvTd7Xu_RBgYw8tjoejaBg",
      "text": "Hi bro",
      "likes": 1,
      "timestamp": 1703376000,
      "parent": "root",
      "is_reply": false
    },
    {
      "author": "@crisreina4954",
      "author_id": "UCx4c0OQYaJcLxT_hDyNTkyg",
      "text": "Qlq gente bella",
      "likes": 1,
      "timestamp": 1734998400,
      "parent": "root",
      "is_reply": false
    },
    {
      "author": "@niallg1220",
      "author_id": "UCLhcqs12UMQeF7MZjUBG7ZQ",
      "text": "1.9k views",
      "likes": 0,
      "timestamp": 1514073600,
      "parent": "root",
      "is_reply": false
    },
    {
      "author": "@alessandrorossi5848",
      "author_id": "UCxKWJIGgFaWAP1JpmFEXOBw",
      "text": "100m",
      "likes": 1,
      "timestamp": 1671840000,
      "parent": "root",
      "is_reply": false
    },
    {
      "author": "@armenianhighland6810",
      "author_id": "UCQ8mYgKV-IYKR_FsFSiXB3w",
      "text": "Hi Mr. Beast",
      "likes": 0,
      "timestamp": 1703376000,
      "parent": "root",
      "is_reply": false
    },
    {
      "author": "@Esybon",
      "author_id": "UCZGljAdKNqKAptB_YiMYOHQ",
      "text": "W Mrbeast6000",
      "likes": 2,
      "timestamp": 1734998400,
      "parent": "root",
      "is_reply": false
    },
    {
      "author": "@yanofajardo-k3f",
      "author_id": "UCdtOEdKNIdY03Ug2ZL2INOQ",
      "text": "Whats up",
      "likes": 1,
      "timestamp": 1734998400,
      "parent": "root",
      "is_reply": false
    },
    {
      "author": "@sammaldonado8301",
      "author_id": "UCKxXR_SKUtos2LEupy4lZag",
      "text": "Mister beast",
      "likes": 1,
      "timestamp": 1753315200,
      "parent": "root",
      "is_reply": false
    },
    {
      "author": "@zidni4554",
      "author_id": "UC-D-6jF7spSdNJLlDXASJAA",
      "text": "😅",
      "likes": 0,
      "timestamp": 1703376000,
      "parent": "root",
      "is_reply": false
    },
    {
      "author": "@nagagutti8432",
      "author_id": "UCbH0hNpX_mIpAO80xGJQmSA",
      "text": "282",
      "likes": 0,
      "timestamp": 1640304000,
      "parent": "root",
      "is_reply": false
    },
    {
      "author": "@EduCaal",
      "author_id": "UCb4JJaK0d5GEHBhvAEFpDvg",
      "text": "Please",
      "likes": 0,
      "timestamp": 1703376000,
      "parent": "root",
      "is_reply": false
    },
    {
      "author": "@Jorgw_Villarreall",
      "author_id": "UCdIRwOnTfzGfay1R5lS9atg",
      "text": "less seen",
      "likes": 2,
      "timestamp": 1734998400,
      "parent": "root",
      "is_reply": false
    },
    {
      "author": "@Jordan4U",
      "author_id": "UCgh-SVLa45omvWMQIymzS0w",
      "text": "This",
      "likes": 1,
      "timestamp": 1734998400,
      "parent": "root",
      "is_reply": false
    },
    {
      "author": "@Nantesminis",
      "author_id": "UCm7wphDykgSAOsbw2OmVWUw",
      "text": "Hiiii",
      "likes": 0,
      "timestamp": 1703376000,
      "parent": "root",
      "is_reply": false
    },
    {
      "author": "@ederstevenpenaquiroga229",
      "author_id": "UCVcWoCVJ_vS4I-TtFiQ7ksw",
      "text": "Xd",
      "likes": 0,
      "timestamp": 1671840000,
      "parent": "root",
      "is_reply": false
    },
    {
      "author": "@MyRzuk12345",
      "author_id": "UCmb385ehepDT5-Xlh3Go8uQ",
      "text": "Почему я сюда зашел? Я незнаю лол",
      "likes": 2,
      "timestamp": 1761264000,
      "parent": "root",
      "is_reply": false
    },
    {
      "author": "@K0C4KK",
      "author_id": "UCGCspsnqEW9Z3qfXwOTGACg",
      "text": "40k view",
      "likes": 0,
      "timestamp": 1703376000,
      "parent": "root",
      "is_reply": false
    },
    {
      "author": "@mrstupiduniverse731c",
      "author_id": "UCOqSC3kl-SjuFBEvPZkAJXA",
      "text": "i forgot what i have",
      "likes": 0,
      "timestamp": 1608768000,
      "parent": "root",
      "is_reply": false
    },
    {
      "author": "@vampde",
      "author_id": "UCRCZAsINaA7A-60Wmz-kzEA",
      "text": "2019 anyone?",
      "likes": 2,
      "timestamp": 1577145600,
      "parent": "root",
      "is_reply": false
    },
    {
      "author": "@OyunTeknesi-qt8wf",
      "author_id": "UCobA9bsjqErBa4DL7jq8acQ",
      "text": "Türkiye",
      "likes": 1,
      "timestamp": 1734998400,
      "parent": "root",
      "is_reply": false
    },
    {
      "author": "@Sachin-D-Rai",
      "author_id": "UCND0KmGS1T8xoA-J8jZANNw",
      "text": "12k views",
      "likes": 0,
      "timestamp": 1640304000,
      "parent": "root",
      "is_reply": false
    },
    {
      "author": "@кириллчигинцев-п9ж",
      "author_id": "UCHLh2WBdl2AUwwf4fRidYAg",
      "text": "Самое не популярное видео на этом канале",
      "likes": 1,
      "timestamp": 1742774400,
      "parent": "root",
      "is_reply": false
    },
    {
      "author": "@theraveninyourbackyard2467",
      "author_id": "UCSpyEDiWFe8YcBFUQvy9e_Q",
      "text": "Who is waching this in 2022",
      "likes": 3,
      "timestamp": 1703376000,
      "parent": "root",
      "is_reply": false
    },
    {
      "author": "@parth_sisodiya",
      "author_id": "UCDsugLbxXXwsonFIFbnMeTA",
      "text": "Omg only 189 comments",
      "likes": 0,
      "timestamp": 1671840000,
      "parent": "root",
      "is_reply": false
    },
    {
      "author": "@abdulkadirtoprak8523",
      "author_id": "UCUg7BxX-Bm3nLY0UZHKckCQ",
      "text": "Vav 😅yes",
      "likes": 0,
      "timestamp": 1703376000,
      "parent": "root",
      "is_reply": false
    },
    {
      "author": "@hilariusleffering4069",
      "author_id": "UCbQiuzfs4oKNoOu586X-_vA",
      "text": "Heyy mr beast can i get a milion for my grandpa",
      "likes": 1,
      "timestamp": 1671840000,
      "parent": "root",
      "is_reply": false
    },
    {
      "author": "@PesokStyle",
      "author_id": "UCZZC36hGJLS11DyFTLVBYKQ",
      "text": "hi",
      "likes": 0,
      "timestamp": 1640304000,
      "parent": "root",
      "is_reply": false
    },
    {
      "author": "@picklecraft164",
      "author_id": "UChmXDJni4anSXNuFv8jUkNQ",
      "text": "Hi",
      "likes": 0,
      "timestamp": 1640304000,
      "parent": "root",
      "is_reply": false
    },
    {
      "author": "@Simjim_32",
      "author_id": "UCYj82whp2Qryndp_hXgIqBQ",
      "text": "Up by only 1 view!",
      "likes": 1,
      "timestamp": 1748044800,
      "parent": "root",
      "is_reply": false
    },
    {
      "author": "@flamewynn4802",
      "author_id": "UCy1hc1VF3ZOcGyFFlin7woA",
      "text": "The least viewed Mr beast vid",
      "likes": 1,
      "timestamp": 1671840000,
      "parent": "root",
      "is_reply": false
    },
    {
      "author": "@amrramdoun",
      "author_id": "UCVftT-w3uZt1yU_INg7jFng",
      "text": "Please make giveaway for Syrian people 🙂",
      "likes": 1,
      "timestamp": 1671840000,
      "parent": "root",
      "is_reply": false
    },
    {
      "author": "@안된다-toRldi",
      "author_id": "UC7NjEQIo1MmhkxhQi1DqoIw",
      "text": "여기 한국인 ㅈㄴ많네 ㅋㅋ",
      "likes": 1,
      "timestamp": 1742774400,
      "parent": "root",
      "is_reply": false
    },
    {
      "author": "@LautaroSartor",
      "author_id": "UCmWSEVgvTj0gF8I9DWJNpww",
      "text": "2023 algueb",
      "likes": 2,
      "timestamp": 1703376000,
      "parent": "root",
      "is_reply": false
    },
    {
      "author": "@user-gm7sw3nv7p",
      "author_id": "UCtYKCFwDluSMX1FJ14a4HdA",
      "text": "282❤",
      "likes": 0,
      "timestamp": 1703376000,
      "parent": "root",
      "is_reply": false
    },
    {
      "author": "@user-fx3qu6un9z",
      "author_id": "UC_QtL89gI6ie-VTqrMR9fcQ",
      "text": "Suuuuuuuuuuper 🔥🔥🔥❤️❤️❤️🎈🎯🎆🍫🧁🧡🎇⚾💪🧨😘🛑💙🎨🚀😃🎊🎱👍🛩️🥎🍩⚽😉🎉❣️💛💛🍭🍭🎀🎀🏐🏐🏀🍰❤️🏈😃🎊🎱🎨👍👍🛑🎀🥎😘🥎🍩🍩💪⚽😉⚾⚾🎇🧡🧨🧁🧁🔥🛑💙💙🎨🎨🚀🎯🎈😃🎊🎱👍🏐🎀🍭🍭💛💛❣️🎉🎉😉⚽🧨🧨🧁🧁🧁🧁🧁🧁🧁🎨🎨🎨🎨🎨🎨🎨🎨🎆🎯🚀🎈🏈❤️❤️🍰🏀🏀🎱🚀🎆🎆🎱🎨💙🔥👍🏐🎀🛩️🛑🔥🎀🎀🍭🥎😘🧡🥎🍭💛🍩🧨🧡💪⚽❣️❣️🎉😉⚾🤎💪🧨🍩🍩🥎🥎🛩️🎨🎨🎨🎱🛩️🥎🥎💛❣️🎉😉⚽🍩🥎🛩️👍🏀🎱🍰❤️🏈😃🚀🎈🎯🎨💙👍🎱👍👍🛑🔥🎨🛑🔥🛑🍩🏐❤️❤️👍🎀💛❣️M",
      "likes": 0,
      "timestamp": 1671840000,
      "parent": "root",
      "is_reply": false
    },
    {
      "author": "@Leonard-pj8io",
      "author_id": "UC37kG3QaKcATITIHSfN4Ozw",
      "text": "Three thousand vive 😅😅",
      "likes": 0,
      "timestamp": 1703376000,
      "parent": "root",
      "is_reply": false
    },
    {
      "author": "@JiulyOp",
      "author_id": "UCSntD27wDAurWzKAQ8ow-KA",
      "text": "Был здесь до 2023!",
      "likes": 1,
      "timestamp": 1703376000,
      "parent": "root",
      "is_reply": false
    },
    {
      "author": "@adriano485",
      "author_id": "UChrkmOGcWq9vRbm6CrKhR7g",
      "text": "Are you still using your PS4?",
      "likes": 0,
      "timestamp": 1608768000,
      "parent": "root",
      "is_reply": false
    },
    {
      "author": "@Carlos-h4r2k",
      "author_id": "UCuYQl-ljsrpXMpwLHZ-GlqQ",
      "text": "This",
      "likes": 1,
      "timestamp": 1748044800,
      "parent": "root",
      "is_reply": false
    },
    {
      "author": "@yui_wa7",
      "author_id": "UCibaI4vrLiz3Xbw57qQNXdw",
      "text": "517th comment!",
      "likes": 1,
      "timestamp": 1734998400,
      "parent": "root",
      "is_reply": false
    },
    {
      "author": "@LemonadeRoblox",
      "author_id": "UCoiJTUppxODlmz3t-NuZPXg",
      "text": "UWU hi mrbeast",
      "likes": 0,
      "timestamp": 1671840000,
      "parent": "root",
      "is_reply": false
    },
    {
      "author": "@NidiaAcosta7",
      "author_id": "UCHoHUEyBClqAAYA-3aH1hiw",
      "text": "Hello",
      "likes": 0,
      "timestamp": 1671840000,
      "parent": "root",
      "is_reply": false
    },
    {
      "author": "@Ronax-e2v",
      "author_id": "UCkxXvudp8jwL7S4RymIM0Tw",
      "text": "Salut",
      "likes": 0,
      "timestamp": 1742774400,
      "parent": "root",
      "is_reply": false
    },
    {
      "author": "@mestorelbs2131",
      "author_id": "UCKAG0FHHsBvlyJTOxYUJmDw",
      "text": "Y",
      "likes": 0,
      "timestamp": 1671840000,
      "parent": "root",
      "is_reply": false
    },
    {
      "author": "@Hobo38",
      "author_id": "UCnl1_Z63O2YKFCP2h1IGfcw",
      "text": "what.?",
      "likes": 0,
      "timestamp": 1703376000,
      "parent": "root",
      "is_reply": false
    },
    {
      "author": "@Angelfabonyt",
      "author_id": "UCTAQ46QOUbtKik_aSjK21Gg",
      "text": "EL GATO",
      "likes": 0,
      "timestamp": 1671840000,
      "parent": "root",
      "is_reply": false
    },
    {
      "author": "@mishutka2914",
      "author_id": "UCWexHgdtOfIywJiyrQcEmFg",
      "text": "Hello Ĥölà Привет",
      "likes": 0,
      "timestamp": 1703376000,
      "parent": "root",
      "is_reply": false
    },
    {
      "author": "@Camcod10",
      "author_id": "UCA8MN-q_PMJJY1qXnZvHO9A",
      "text": "I have a question about the elgato. Will I have to record my sound with another program or does the elgato come with a built - in microphone?",
      "likes": 5,
      "timestamp": 1450915200,
      "parent": "root",
      "is_reply": false
    },
    {
      "author": "@mgromar2315",
      "author_id": "UC2Gzduuq4aGPpElofMsf8YA",
      "text": "15k Views 🤣",
      "likes": 0,
      "timestamp": 1671840000,
      "parent": "root",
      "is_reply": false
    },
    {
      "author": "@BusetGt",
      "author_id": "UCBiugzuAloRcpONRyNm286A",
      "text": "lol 36 k views",
      "likes": 1,
      "timestamp": 1703376000,
      "parent": "root",
      "is_reply": false
    },
    {
      "author": "@potatohmm",
      "author_id": "UCZElwrb7efLm2iObMVC_C5Q",
      "text": "This is the least favourite views in your channel",
      "likes": 3,
      "timestamp": 1703376000,
      "parent": "root",
      "is_reply": false
    },
    {
      "author": "@Phinz101",
      "author_id": "UCNPAS2IUkCGqZh6di_DgbEw",
      "text": "So this is his least popular vid",
      "likes": 1,
      "timestamp": 1703376000,
      "parent": "root",
      "is_reply": false
    },
    {
      "author": "@jevgenijlasakevic6993",
      "author_id": "UCg7Rl0-5SxQRi9x8lOYEUkA",
      "text": "292",
      "likes": 1,
      "timestamp": 1745452800,
      "parent": "root",
      "is_reply": false
    },
    {
      "author": "@Muzikhane_1",
      "author_id": "UCllrR2wlr7-pI3EjEBXjVtg",
      "text": "Hello",
      "likes": 0,
      "timestamp": 1703376000,
      "parent": "root",
      "is_reply": false
    },
    {
      "author": "@tataolam4168",
      "author_id": "UCDeLfL2MfXTrMSZYw-O5FTg",
      "text": "191th comment lol",
      "likes": 0,
      "timestamp": 1671840000,
      "parent": "root",
      "is_reply": false
    },
    {
      "author": "@eroszoppas6103",
      "author_id": "UC4oa9zICE5ZnUn5tkkyimpA",
      "text": "🇮🇹",
      "likes": 0,
      "timestamp": 1671840000,
      "parent": "root",
      "is_reply": false
    },
    {
      "author": "@KotalissFamilyVids",
      "author_id": "UCtRh-jha37zzt272ztZdWSg",
      "text": "But",
      "likes": 0,
      "timestamp": 1608768000,
      "parent": "root",
      "is_reply": false
    },
    {
      "author": "@solarz_z",
      "author_id": "UC6jTRCMSHSNWeygrVnsZ63w",
      "text": "33k views.",
      "likes": 0,
      "timestamp": 1703376000,
      "parent": "root",
      "is_reply": false
    },
    {
      "author": "@Solid.Worlds",
      "author_id": "UCpCx77LZyEMUHthuix4Glbg",
      "text": "Finnaly, after hours of scrolling, I have arrived...",
      "likes": 0,
      "timestamp": 1671840000,
      "parent": "root",
      "is_reply": false
    },
    {
      "author": "@AloneSitoYT",
      "author_id": "UCD_wFh0bqCZ8y5pkUfiUNJA",
      "text": "Wassup this is one of the less watched MrBeast videos :) hello if you see this comment :D",
      "likes": 1,
      "timestamp": 1671840000,
      "parent": "root",
      "is_reply": false
    },
    {
      "author": "@SipDisco",
      "author_id": "UC-1L-fruU7_1kh-2gz8ByBA",
      "text": "Who's here in 2022? LOL",
      "likes": 1,
      "timestamp": 1671840000,
      "parent": "root",
      "is_reply": false
    },
    {
      "author": "@jeremiasrojas-dx1ys",
      "author_id": "UCxJbQYKBRmtRat9EJzr_R4w",
      "text": "Mr.beast sigueme plis",
      "likes": 0,
      "timestamp": 1703376000,
      "parent": "root",
      "is_reply": false
    },
    {
      "author": "@bruhapss",
      "author_id": "UCPL-59KSkSEfsK_hwrdYVrQ",
      "text": "Are you still using your PS4 after 8 years @MrBeast ???",
      "likes": 1,
      "timestamp": 1734998400,
      "parent": "root",
      "is_reply": false
    },
    {
      "author": "@tia809",
      "author_id": "UC_qDJtEK2AdSrFaH6WQvxnA",
      "text": "Bruh",
      "likes": 0,
      "timestamp": 1703376000,
      "parent": "root",
      "is_reply": false
    },
    {
      "author": "@kingarehman142",
      "author_id": "UCUWj2yfX_BXiufDtaL5Rxwg",
      "text": "Amogus",
      "likes": 1,
      "timestamp": 1671840000,
      "parent": "root",
      "is_reply": false
    },
    {
      "author": "@lordbeerus3267",
      "author_id": "UC20l_rI0LV2XYLGH6xaVEEw",
      "text": "69,420",
      "likes": 0,
      "timestamp": 1640304000,
      "parent": "root",
      "is_reply": false
    },
    {
      "author": "@Jacob2508",
      "author_id": "UCDEnLxOe3BGzXaLlG3P4nBQ",
      "text": "Can I have an Samsung (2024 lottery)",
      "likes": 0,
      "timestamp": 1734998400,
      "parent": "root",
      "is_reply": false
    },
    {
      "author": "@walter_causa",
      "author_id": "UCW2Lla4rqRq0yOEP277RqQw",
      "text": "least viewed video",
      "likes": 4,
      "timestamp": 1734998400,
      "parent": "root",
      "is_reply": false
    },
    {
      "author": "@Arch-Bro1",
      "author_id": "UCNJdW8ODokFGZs0k0ZsX2dQ",
      "text": "Mr beast",
      "likes": 0,
      "timestamp": 1703376000,
      "parent": "root",
      "is_reply": false
    },
    {
      "author": "@Popenduk",
      "author_id": "UCLm7lNZf541fXy7p867jPnQ",
      "text": "Аовшал",
      "likes": 0,
      "timestamp": 1703376000,
      "parent": "root",
      "is_reply": false
    },
    {
      "author": "@DoctorSoap_Sing",
      "author_id": "UCJfqbiXujLb-2goZ72h8PgA",
      "text": "284",
      "likes": 0,
      "timestamp": 1745452800,
      "parent": "root",
      "is_reply": false
    },
    {
      "author": "@Kazandra24forever",
      "author_id": "UCPllaSvRWk5EnXTo3cpAObw",
      "text": "34raaduei",
      "likes": 0,
      "timestamp": 1640304000,
      "parent": "root",
      "is_reply": false
    },
    {
      "author": "@IntentionalFootball",
      "author_id": "UCRJoZFnPblRe1Yqk06Wz3KA",
      "text": "simp for",
      "likes": 0,
      "timestamp": 1671840000,
      "parent": "root",
      "is_reply": false
    },
    {
      "author": "@EdwardPhil-z1m",
      "author_id": "UCJAiPWENtdKBqLQM30RqeKQ",
      "text": "Mr beast 6000",
      "likes": 1,
      "timestamp": 1703376000,
      "parent": "root",
      "is_reply": false
    },
    {
      "author": "@4ak_4ak228",
      "author_id": "UCeGD7yR_JJ0x6kt6hlxBtrQ",
      "text": "Most unpopular 😅",
      "likes": 1,
      "timestamp": 1734998400,
      "parent": "root",
      "is_reply": false
    },
    {
      "author": "@wisatya29",
      "author_id": "UCoX7BK_vpY-Tj5W15gsgNcQ",
      "text": "Sepi wkwkwwkwk",
      "likes": 1,
      "timestamp": 1703376000,
      "parent": "root",
      "is_reply": false
    },
    {
      "author": "@irvingalexanderll9880",
      "author_id": "UC2PLt-wQkVV7K-sswsnSMVw",
      "text": ":0",
      "likes": 0,
      "timestamp": 1703376000,
      "parent": "root",
      "is_reply": false
    },
    {
      "author": "@EymenYetkin-z7h",
      "author_id": "UCvCnqUksWzCiWCd2JEZdUww",
      "text": "Last viewed",
      "likes": 2,
      "timestamp": 1734998400,
      "parent": "root",
      "is_reply": false
    },
    {
      "author": "@Darius12-1",
      "author_id": "UCL8euPU7ZT5PIy_Sn7qWNXQ",
      "text": "I don’t under stand this grilled cheese Obama sandwich",
      "likes": 0,
      "timestamp": 1703376000,
      "parent": "root",
      "is_reply": false
    },
    {
      "author": "@indomie3k",
      "author_id": "UCL4GFxA-SiPT80_wDITQglQ",
      "text": "Hello am in the water please help me 😢",
      "likes": 0,
      "timestamp": 1703376000,
      "parent": "root",
      "is_reply": false
    },
    {
      "author": "@applekid321",
      "author_id": "UCo35oeUbRbp-Qbv-oAFDaxw",
      "text": "Do a Youtubers that have died list\nOr if there's none do a likely  to die list",
      "likes": 0,
      "timestamp": 1450915200,
      "parent": "root",
      "is_reply": false
    },
    {
      "author": "@HandIe564",
      "author_id": "UCecPXuzMzreClgY9qW5Z5_A",
      "text": "People who scrolled all the way down just to see his least viewed video:",
      "likes": 1,
      "timestamp": 1734998400,
      "parent": "root",
      "is_reply": false
    },
    {
      "author": "@Thatonekid3766",
      "author_id": "UC2Ie7rheP5KNEUMejL6651g",
      "text": "Puppy",
      "likes": 0,
      "timestamp": 1703376000,
      "parent": "root",
      "is_reply": false
    },
    {
      "author": "@jojoLeader",
      "author_id": "UCGAlyUeY9amNDrhh2VCkc5A",
      "text": "281번째 댓글입니다. 미스터 비스트!! 지금 내가 하는 챌린지가 별것 아니지만 좋은 결과가 생겼으면 좋겠다 ㅎㅎ  Challenge! My goal is to get a ❤ from you!",
      "likes": 0,
      "timestamp": 1703376000,
      "parent": "root",
      "is_reply": false
    },
    {
      "author": "@selenakecubity",
      "author_id": "UC8qskHmaj6u_008StfqvA3Q",
      "text": "Novaria",
      "likes": 0,
      "timestamp": 1703376000,
      "parent": "root",
      "is_reply": false
    },
    {
      "author": "@freepalestine.-.",
      "author_id": "UCVvNJ-8xZaswNmDfUYWnHaw",
      "text": "Yow",
      "likes": 1,
      "timestamp": 1703376000,
      "parent": "root",
      "is_reply": false
    },
    {
      "author": "@PointFear",
      "author_id": "UCSDrbvN7F_WEutfzuFZGQiw",
      "text": "Least views in ur vid",
      "likes": 5,
      "timestamp": 1671840000,
      "parent": "root",
      "is_reply": false
    },
    {
      "author": "@dvireizonshabang_d7708",
      "author_id": "UCuORU7XSf4-_YlcJUkJ6JKQ",
      "text": "thats your least viewed vid",
      "likes": 1,
      "timestamp": 1671840000,
      "parent": "root",
      "is_reply": false
    },
    {
      "author": "@MysticMEE",
      "author_id": "UChO6-kMyYjra22uv-6r0eww",
      "text": "What's the name of the outro song? The description link isn't updated.",
      "likes": 1,
      "timestamp": 1450915200,
      "parent": "root",
      "is_reply": false
    },
    {
      "author": "@EthanSchriver",
      "author_id": "UC6A6ONu3ZDyRLgmp_paLMvg",
      "text": "I still have your roxio :/ lol want it back? xD",
      "likes": 1,
      "timestamp": 1450915200,
      "parent": "root",
      "is_reply": false
    },
    {
      "author": "@cubicblue6655",
      "author_id": "UCTXhtS8eDUg2iOKqT6dYdIQ",
      "text": "video is \"should I buy an elgato\" yet you've already bought it lol",
      "likes": 1,
      "timestamp": 1450915200,
      "parent": "root",
      "is_reply": false
    },
    {
      "author": "@hray60",
      "author_id": "UCbzcuxlyQxPlgj2Q3Tn4HJA",
      "text": "Please can I have your old recording thing please ",
      "likes": 0,
      "timestamp": 1450915200,
      "parent": "root",
      "is_reply": false
    },
    {
      "author": "@3zfi",
      "author_id": "UCbD5EqoIwwcUeI9spHvV8Og",
      "text": "الوووووووووووووو😶‍🌫️",
      "likes": 1,
      "timestamp": 1671840000,
      "parent": "root",
      "is_reply": false
    },
    {
      "author": "@johnmcgowan7621",
      "author_id": "UCUswwHDoeck8C8WRm8C6I-A",
      "text": "Any one from 2018",
      "likes": 1,
      "timestamp": 1545609600,
      "parent": "root",
      "is_reply": false
    },
    {
      "author": "@nolaan7",
      "author_id": "UCVsBeaqd0bDiNUzlynQYW5w",
      "text": "36K veiws is too little for such a youruber",
      "likes": 0,
      "timestamp": 1703376000,
      "parent": "root",
      "is_reply": false
    },
    {
      "author": "@Liama_221",
      "author_id": "UCgRIr6Qs8FCq9ooiNN7UQTA",
      "text": "Anjir sepi🗿",
      "likes": 0,
      "timestamp": 1703376000,
      "parent": "root",
      "is_reply": false
    },
    {
      "author": "@pauliewalnutsgualtieri8779",
      "author_id": "UCcWEeiqaOqJ5i9QbmTBn7qA",
      "text": "mr beast what is your laptop specs im trying to buy me a good gaming computer and need some suggestions.",
      "likes": 0,
      "timestamp": 1450915200,
      "parent": "root",
      "is_reply": false
    },
    {
      "author": "@gallazyeggaseli",
      "author_id": "UChBWRrvSycx_l5Y3RVtC_8A",
      "text": "42VIEWS?",
      "likes": 0,
      "timestamp": 1703376000,
      "parent": "root",
      "is_reply": false
    },
    {
      "author": "@splashythefish2071",
      "author_id": "UCosas5U4O-gMHxoaWpSjoKQ",
      "text": "least viewed vid",
      "likes": 2,
      "timestamp": 1703376000,
      "parent": "root",
      "is_reply": false
    },
    {
      "author": "@josebeto06",
      "author_id": "UCFJt3RtGwSzDbUoXWursznQ",
      "text": "2023😢?",
      "likes": 0,
      "timestamp": 1703376000,
      "parent": "root",
      "is_reply": false
    },
    {
      "author": "@josebeto06",
      "author_id": "UCFJt3RtGwSzDbUoXWursznQ",
      "text": "2023😢?",
      "likes": 0,
      "timestamp": 1703376000,
      "parent": "root",
      "is_reply": false
    },
    {
      "author": "@josebeto06",
      "author_id": "UCFJt3RtGwSzDbUoXWursznQ",
      "text": "2023😢?",
      "likes": 0,
      "timestamp": 1703376000,
      "parent": "root",
      "is_reply": false
    },
    {
      "author": "@kaitran",
      "author_id": "UC4gp6H_g9pSm4VdDm0YMqww",
      "text": "1 mil 2 years",
      "likes": 0,
      "timestamp": 1514073600,
      "parent": "root",
      "is_reply": false
    },
    {
      "author": "@氣Pluh",
      "author_id": "UCSXp1Bmx01hhkRN2qM4bjIQ",
      "text": "Advertise me to get absolutely nothing",
      "likes": 0,
      "timestamp": 1703376000,
      "parent": "root",
      "is_reply": false
    },
    {
      "author": "@f14m3dd",
      "author_id": "UCiyYmFn0Hmgo0HTQF0EzwdA",
      "text": "Mr beast notice this comment and give me $100 or I will cgdt dakdj",
      "likes": 2,
      "timestamp": 1734998400,
      "parent": "root",
      "is_reply": false
    },
    {
      "author": "@Bolt17",
      "author_id": "UCtrk75Q11U-C2EY9bQg3Irw",
      "text": "This is his least viewed vid lol",
      "likes": 0,
      "timestamp": 1703376000,
      "parent": "root",
      "is_reply": false
    },
    {
      "author": "@bup23",
      "author_id": "UCfp1zIs-ujlZIyO9JhMNrZQ",
      "text": "Least viewed mrbeast vid",
      "likes": 0,
      "timestamp": 1671840000,
      "parent": "root",
      "is_reply": false
    },
    {
      "author": "@ossoissi2464",
      "author_id": "UC9Vsf589NPY8bRhYdeNAGSQ",
      "text": "Sepi bjir",
      "likes": 1,
      "timestamp": 1703376000,
      "parent": "root",
      "is_reply": false
    },
    {
      "author": "@jack3d88d2",
      "author_id": "UCR77P7_dOmxH4T-oV39qnKA",
      "text": "FIRST",
      "likes": 1,
      "timestamp": 1671840000,
      "parent": "root",
      "is_reply": false
    },
    {
      "author": "@Yanetvelazco-q4u",
      "author_id": "UCNWseF2RUYJwgAby82ODl_g",
      "text": "Ñ",
      "likes": 0,
      "timestamp": 1745452800,
      "parent": "root",
      "is_reply": false
    },
    {
      "author": "@goofiestdj3",
      "author_id": "UCdkbd0P63Mvw8lm73rm4K7A",
      "text": "El gato 🐱 🐈🐈‍⬛🐱🐈🐈‍⬛🐈🐈‍⬛🐈‍⬛🐈‍⬛🐈🐈‍⬛🐱🐈🐱🐈🐱🐈‍⬛🐱🐈‍⬛🐱🐈",
      "likes": 0,
      "timestamp": 1671840000,
      "parent": "root",
      "is_reply": false
    },
    {
      "author": "@Mr.Anonimus7",
      "author_id": "UCo9tFjEdgoSVudsYoG5mCpw",
      "text": "Pe",
      "likes": 0,
      "timestamp": 1703376000,
      "parent": "root",
      "is_reply": false
    },
    {
      "author": "@cahyojawir",
      "author_id": "UCpI8TW4TmNC9aqx4HiQM9rQ",
      "text": "Sepi",
      "likes": 1,
      "timestamp": 1703376000,
      "parent": "root",
      "is_reply": false
    },
    {
      "author": "@ItsALaughYT",
      "author_id": "UCekUb0KFeZs0rD_7sWOnCrA",
      "text": "Buy a car",
      "likes": 0,
      "timestamp": 1577145600,
      "parent": "root",
      "is_reply": false
    },
    {
      "author": "@420Euser69th",
      "author_id": "UCV3Y6x76RSlGPR9VQeOYU1g",
      "text": "Least view Mr beast video",
      "likes": 0,
      "timestamp": 1734998400,
      "parent": "root",
      "is_reply": false
    },
    {
      "author": "@Fallzzz.",
      "author_id": "UCzLxijro5YmHDN8ScH3Hlmg",
      "text": "🗿Langsung kesini kan kalian para indo",
      "likes": 0,
      "timestamp": 1703376000,
      "parent": "root",
      "is_reply": false
    },
    {
      "author": "@hypersonicdashhkevin",
      "author_id": "UCQ-4xiSVI7_kpM-PDCt_eOQ",
      "text": "this vid did trash \nmost unpopular vid on the mr beast channel",
      "likes": 1,
      "timestamp": 1703376000,
      "parent": "root",
      "is_reply": false
    },
    {
      "author": "@alhafis8539",
      "author_id": "UCmCDLxl2HwpFJTa0w_I1WMg",
      "text": "P",
      "likes": 0,
      "timestamp": 1703376000,
      "parent": "root",
      "is_reply": false
    },
    {
      "author": "@SecretJiangLai1123",
      "author_id": "UCqItQWleXlCb1Xa5ZDNhnhw",
      "text": "the least viewed vid",
      "likes": 2,
      "timestamp": 1734998400,
      "parent": "root",
      "is_reply": false
    },
    {
      "author": "@NotSoFancyGames",
      "author_id": "UCUMLWCOuV37n_csEc3RJupw",
      "text": "Why can't you render a video with a 720p clip in 1080p? they are the same aspect ratio so it would be fine",
      "likes": 6,
      "timestamp": 1450915200,
      "parent": "root",
      "is_reply": false
    },
    {
      "author": "@percival_salad",
      "author_id": "UCYL1Yx72Z9fxeckJ1jo0_AQ",
      "text": "least viewed",
      "likes": 3,
      "timestamp": 1671840000,
      "parent": "root",
      "is_reply": false
    },
    {
      "author": "@cubicblue6655",
      "author_id": "UCTXhtS8eDUg2iOKqT6dYdIQ",
      "text": "what is that outro song? update your description man. and also what's that background song you've been using a lot lately?",
      "likes": 0,
      "timestamp": 1450915200,
      "parent": "root",
      "is_reply": false
    },
    {
      "author": "@ryrykovi4227",
      "author_id": "UCIPKdCrKGzNVwIJRaQvGOaw",
      "text": "Jesus. loves. You",
      "likes": 2,
      "timestamp": 1640304000,
      "parent": "root",
      "is_reply": false
    },
    {
      "author": "@ecocideclokktail",
      "author_id": "UCChXNZmSvafmBkLTnfMRzkA",
      "text": "this is his least viewed vid :)",
      "likes": 0,
      "timestamp": 1671840000,
      "parent": "root",
      "is_reply": false
    },
    {
      "author": "@ibradudaev7280",
      "author_id": "UCX0uYKzHiYmDH5FlmSv05UQ",
      "text": "Это видео мистера биста самая не популярная. Давайте соберём много лайков чтоб американцы подумали что комент хороший",
      "likes": 4,
      "timestamp": 1703376000,
      "parent": "root",
      "is_reply": false
    },
    {
      "author": "@NadiaDia-ft1is",
      "author_id": "UCipHqnkZbAfIDdsToNNFGPQ",
      "text": "Siapa ini yang kesini",
      "likes": 0,
      "timestamp": 1703376000,
      "parent": "root",
      "is_reply": false
    },
    {
      "author": "@meninggoy1224",
      "author_id": "UCdAxGIuz4iAzBimY-Jj9tjw",
      "text": "Vidio tersepi mr beast",
      "likes": 4,
      "timestamp": 1703376000,
      "parent": "root",
      "is_reply": false
    },
    {
      "author": "@VizzAj",
      "author_id": "UCf6Get33ITCfv3espg42dXw",
      "text": "P",
      "likes": 0,
      "timestamp": 1703376000,
      "parent": "root",
      "is_reply": false
    },
    {
      "author": "@StasisTV",
      "author_id": "UCVVSHl6jWHSkuMZmvmYfibA",
      "text": "man my elgato looks better then what I am looking at did you render at low settings",
      "likes": 0,
      "timestamp": 1482537600,
      "parent": "root",
      "is_reply": false
    },
    {
      "author": "@pinguin32",
      "author_id": "UCdqomd8gB4MaZSIimpGNXYA",
      "text": "Someone in 2024?",
      "likes": 1,
      "timestamp": 1734998400,
      "parent": "root",
      "is_reply": false
    },
    {
      "author": "@DORAEMON-r2t",
      "author_id": "UC5IHcTYqEx4pYEwEZDWgOzQ",
      "text": "Who is WATCHING THIS VIDEO in 2024",
      "likes": 2,
      "timestamp": 1734998400,
      "parent": "root",
      "is_reply": false
    },
    {
      "author": "@albinef7",
      "author_id": "UCNIkiKSOqpmJLh3g1BMNMig",
      "text": ">buys elgato\n>makes unboxing\n>gets money from unboxing since people love watching them\n>makes money back",
      "likes": 2,
      "timestamp": 1450915200,
      "parent": "root",
      "is_reply": false
    },
    {
      "author": "@LuhLandonn",
      "author_id": "UCGGx1keZBxG5oE2xXUC1JwQ",
      "text": "Least viewed vid",
      "likes": 0,
      "timestamp": 1671840000,
      "parent": "root",
      "is_reply": false
    },
    {
      "author": "@apriciociricio8311",
      "author_id": "UC2lPd8t_5QtXkrMGrWYcFcw",
      "text": "Yesssss plzzzzzzz buy it",
      "likes": 0,
      "timestamp": 1671840000,
      "parent": "root",
      "is_reply": false
    },
    {
      "author": "@648546lllooolll",
      "author_id": "UCbuA6-HOHA-0VVPCrsDOjuA",
      "text": "I'd do ANYTHING just to hang out with these guys for a day.!!!",
      "likes": 1,
      "timestamp": 1640304000,
      "parent": "root",
      "is_reply": false
    },
    {
      "author": "@Darkness_San",
      "author_id": "UC0yoDYP7A1nqx0v74qduKEw",
      "text": "Слава России",
      "likes": 1,
      "timestamp": 1703376000,
      "parent": "root",
      "is_reply": false
    },
    {
      "author": "@rivaldograa6593",
      "author_id": "UCM8BAhsA2RU0q0oIMp-f6Jw",
      "text": "indoo solo?",
      "likes": 2,
      "timestamp": 1703376000,
      "parent": "root",
      "is_reply": false
    },
    {
      "author": "@skraylers",
      "author_id": "UCBfPM_MLhH8OGH1ixaHv3YA",
      "text": "Who's here in 2022 lmao",
      "likes": 4,
      "timestamp": 1671840000,
      "parent": "root",
      "is_reply": false
    },
    {
      "author": "@Nogw21bs",
      "author_id": "UCywZKhDaNhWoG83KXMHdZUw",
      "text": "Those who scrolled \n👇",
      "likes": 7,
      "timestamp": 1750723200,
      "parent": "root",
      "is_reply": false
    },
    {
      "author": "@eabqari",
      "author_id": "UCyKmIo7qVIJc1E6_nmRACoQ",
      "text": "قناه لديها 142 مليون مشترك واكثر ومشاهدات 29000 بس ازاي",
      "likes": 1,
      "timestamp": 1703376000,
      "parent": "root",
      "is_reply": false
    },
    {
      "author": "@elgeren1",
      "author_id": "UCHbxv3z0-JvBG-Igc_b90kA",
      "text": "Anyone in 2047?",
      "likes": 4,
      "timestamp": 1734998400,
      "parent": "root",
      "is_reply": false
    },
    {
      "author": "@ZafarAbdul-nc7bl",
      "author_id": "UCD1fOfmADeKdu5o91PyJ32g",
      "text": "Daddy",
      "likes": 0,
      "timestamp": 1703376000,
      "parent": "root",
      "is_reply": false
    },
    {
      "author": "@marlon8695",
      "author_id": "UCJQEii9kmR3aOGM0trFGxEA",
      "text": "no",
      "likes": 1,
      "timestamp": 1703376000,
      "parent": "root",
      "is_reply": false
    },
    {
      "author": "@ahmadkemnk9594",
      "author_id": "UCrE02NlqVZ74uuh9FIWOmqg",
      "text": "I swear by God Almighty, whoever follows me, will fulfill all your wishes",
      "likes": 0,
      "timestamp": 1671840000,
      "parent": "root",
      "is_reply": false
    },
    {
      "author": "@natemtbaltaccnt",
      "author_id": "UC1V0h_fdlys1ekla719LeIw",
      "text": "Who’s here for the first mrbeast vid",
      "likes": 0,
      "timestamp": 1671840000,
      "parent": "root",
      "is_reply": false
    },
    {
      "author": "@TheEliteMasen",
      "author_id": "UCBrhF73CoPi4oLEqyUJIu1g",
      "text": "no",
      "likes": 0,
      "timestamp": 1671840000,
      "parent": "root",
      "is_reply": false
    }
  ],
  "error": null
}