{
  "video_id": "M94G0iKYiSM",
  "title": "HONEST Shout Out Sunday! Free Subscribers!",
  "url": "https://www.youtube.com/watch?v=M94G0iKYiSM",
  "comment_count": 319,
  "comments": [
    {
      "author": "@SEA-SALT60",
      "author_id": "UCvAg-9CiJTUurd91oQ_dxMQ",
      "text": "This is the least popular mr beast vid",
      "likes": 304,
      "timestamp": 1703376000,
      "parent": "root",
      "is_reply": false
    },
    {
      "author": "@MrBeast",
      "author_id": "UCX6OQ3DkcsbYNE6H8uQQuVA",
      "text": "Sorry about reuploading this, trust me it makes me just as annoyed.",
      "likes": 357,
      "timestamp": 1450915200,
      "parent": "root",
      "is_reply": false
    },
    {
      "author": "@IlyzYT",
      "author_id": "UCbqgLa0I_ByxWdBrCUTFfhg",
      "text": "50k views on jimmys vid is crazy with 300m subs",
      "likes": 29,
      "timestamp": 1734998400,
      "parent": "root",
      "is_reply": false
    },
    {
      "author": "@chrisdaven4775",
      "author_id": "UCg8xKMSNXUFEz6sfZBi8xaA",
      "text": "People who came here to see his least viewed vid",
      "likes": 12,
      "timestamp": 1734998400,
      "parent": "root",
      "is_reply": false
    },
    {
      "author": "@iain3713",
      "author_id": "UCijBNq7RETw-nrhqpaYNWbQ",
      "text": "Someone make a count on how many times beast said subscribe",
      "likes": 21,
      "timestamp": 1450915200,
      "parent": "root",
      "is_reply": false
    },
    {
      "author": "@HH-sleekhool",
      "author_id": "UCAIUZ1tWnuZ1dJm9C9eYy0g",
      "text": "And this is the start of a legend 🌟330M✨",
      "likes": 6,
      "timestamp": 1734998400,
      "parent": "root",
      "is_reply": false
    },
    {
      "author": "@hasanalashari2181",
      "author_id": "UCRpIAdC7F7_9uWYzMz3rAbQ",
      "text": "this is so crazy",
      "likes": 5,
      "timestamp": 1703376000,
      "parent": "root",
      "is_reply": false
    },
    {
      "author": "@anthonycropp9861",
      "author_id": "UCv0I9dHKK3WGs2PyWnHMOYQ",
      "text": "Man this is crazy who knew that being an unsuccessful YouTuber would become one of the best you tubers in the world that’s truly crazy man you the best youtuber out there keep doing what your doing I really love your content man your awesome",
      "likes": 54,
      "timestamp": 1608768000,
      "parent": "root",
      "is_reply": false
    },
    {
      "author": "@indigoselinger1640",
      "author_id": "UCN5yzATFJvIsr6ojZDC28Nw",
      "text": "His least viewed video…I wonder how many of us are time travelers",
      "likes": 14,
      "timestamp": 1671840000,
      "parent": "root",
      "is_reply": false
    },
    {
      "author": "@karenkurlz",
      "author_id": "UCwY4pC7NzXeKcshcLrAvzcg",
      "text": "I loved every second of this! You’re awesome!",
      "likes": 20,
      "timestamp": 1608768000,
      "parent": "root",
      "is_reply": false
    },
    {
      "author": "@NoNameMaks",
      "author_id": "UCDi7spHkFtxoHQCip__kZJg",
      "text": "2023?",
      "likes": 5,
      "timestamp": 1703376000,
      "parent": "root",
      "is_reply": false
    },
    {
      "author": "@WilderSalazarabal",
      "author_id": "UC4tEBKmVR61jXqjj1r98Yfw",
      "text": "Felicidades bajaste tanto y lo encontraste tano un descanso  vaquero o vaquera❤❤❤",
      "likes": 2,
      "timestamp": 1742774400,
      "parent": "root",
      "is_reply": false
    },
    {
      "author": "@zyro.",
      "author_id": "UCFNmtihAHQ6tw8JBjvsGciQ",
      "text": "anyone else here from timeworks?",
      "likes": 3,
      "timestamp": 1703376000,
      "parent": "root",
      "is_reply": false
    },
    {
      "author": "@OnisDomain",
      "author_id": "UC0SUC_Fd-7qUs9yq6T-LtGg",
      "text": "Oh hell I found this lol",
      "likes": 3,
      "timestamp": 1608768000,
      "parent": "root",
      "is_reply": false
    },
    {
      "author": "@joshuakim1497",
      "author_id": "UCPyXnOujlJunzBnquTY9qlw",
      "text": "I'll be a shout-out Sunday 👀",
      "likes": 2,
      "timestamp": 1640304000,
      "parent": "root",
      "is_reply": false
    },
    {
      "author": "@pleasehelp1390",
      "author_id": "UCaM_T3DeGC2TWPE1WXQUj2A",
      "text": "i still love new mr beast but theres a reason why this dude became famous in the first place lmao",
      "likes": 4,
      "timestamp": 1640304000,
      "parent": "root",
      "is_reply": false
    },
    {
      "author": "@FirePosts",
      "author_id": "UCAw8lPtG_1VFYdjfmEbT0BQ",
      "text": "Now a shoutout from mrBeasts gives you millions of subscribers and changes you whole life. :o",
      "likes": 4,
      "timestamp": 1640304000,
      "parent": "root",
      "is_reply": false
    },
    {
      "author": "@desihoff",
      "author_id": "UCN3m8f02Sd68XRnVUjj4JaQ",
      "text": "Love it.",
      "likes": 1,
      "timestamp": 1671840000,
      "parent": "root",
      "is_reply": false
    },
    {
      "author": "@Joethetoolguy",
      "author_id": "UCQcQbHmGyDrf80cb5H4tW7w",
      "text": "Found this and subbed, lol",
      "likes": 1,
      "timestamp": 1640304000,
      "parent": "root",
      "is_reply": false
    },
    {
      "author": "@WondersList",
      "author_id": "UCqD8GmVj6IomjbzVa75XoyQ",
      "text": "Okay I subscribed, I hope I win on next Sunday",
      "likes": 1,
      "timestamp": 1640304000,
      "parent": "root",
      "is_reply": false
    },
    {
      "author": "@pr00bing",
      "author_id": "UCuRXsjzp6GPUsG8BS1WiBNQ",
      "text": "mr beast come to goshen indiana",
      "likes": 2,
      "timestamp": 1703376000,
      "parent": "root",
      "is_reply": false
    },
    {
      "author": "@onstr",
      "author_id": "UCrDsKBylMLXi9L1m96KtSug",
      "text": "You definitely have active subscribers now.",
      "likes": 0,
      "timestamp": 1640304000,
      "parent": "root",
      "is_reply": false
    },
    {
      "author": "@lucas-he5up",
      "author_id": "UCmHF7raUUcNdh2_eP_YAFfQ",
      "text": "hola",
      "likes": 2,
      "timestamp": 1703376000,
      "parent": "root",
      "is_reply": false
    },
    {
      "author": "@catgoatfoxlover",
      "author_id": "UCgx6JXNtVzV57TZRszmeEVg",
      "text": "Watching all his vids!",
      "likes": 0,
      "timestamp": 1640304000,
      "parent": "root",
      "is_reply": false
    },
    {
      "author": "@DekmansAviation",
      "author_id": "UCPnk8cT0QcmYuDjQqpjlUeg",
      "text": "@Mrbeast still shouting out?",
      "likes": 1,
      "timestamp": 1766102400,
      "parent": "root",
      "is_reply": false
    },
    {
      "author": "@tenplusten1116",
      "author_id": "UC3G9y6AHWCYZP39EJWP_EYQ",
      "text": "here from timeworks =)",
      "likes": 2,
      "timestamp": 1703376000,
      "parent": "root",
      "is_reply": false
    },
    {
      "author": "@Hc么",
      "author_id": "UCrTT6vRdmG4ZsGp5EZ2B-7w",
      "text": "How are you bro?",
      "likes": 3,
      "timestamp": 1703376000,
      "parent": "root",
      "is_reply": false
    },
    {
      "author": "@jp-si5yv",
      "author_id": "UCQ497RLMJM9bTzEeHUD9FAQ",
      "text": "bro this man is so different",
      "likes": 1,
      "timestamp": 1671840000,
      "parent": "root",
      "is_reply": false
    },
    {
      "author": "@maddie8239",
      "author_id": "UCp2PKzJ7-VCC6MV9aom9FYw",
      "text": "I'll take one",
      "likes": 1,
      "timestamp": 1608768000,
      "parent": "root",
      "is_reply": false
    },
    {
      "author": "@arcane1204",
      "author_id": "UC28avVXMfLj38JNEkP1W3-Q",
      "text": "lets go mrbeast",
      "likes": 0,
      "timestamp": 1671840000,
      "parent": "root",
      "is_reply": false
    },
    {
      "author": "@maximo_editsz",
      "author_id": "UCVPSuF2AdBb-0v8BPP4eaKg",
      "text": "El vídeo menos popular de el señor bestia☠️🔥",
      "likes": 1,
      "timestamp": 1750723200,
      "parent": "root",
      "is_reply": false
    },
    {
      "author": "@sly2sal298",
      "author_id": "UCYgzVc7ENo9SjN55dJ73e-g",
      "text": "Yay free stuff",
      "likes": 0,
      "timestamp": 1640304000,
      "parent": "root",
      "is_reply": false
    },
    {
      "author": "@saramursalim3942",
      "author_id": "UC4fey_Va_Pzz46trubjeESQ",
      "text": "been doin it since he was young",
      "likes": 0,
      "timestamp": 1608768000,
      "parent": "root",
      "is_reply": false
    },
    {
      "author": "@wongtonggongbong2521",
      "author_id": "UCKk9XvUzVfZXdHDl5yU3bHg",
      "text": "WOOHOO",
      "likes": 2,
      "timestamp": 1577145600,
      "parent": "root",
      "is_reply": false
    },
    {
      "author": "@imnadzeN",
      "author_id": "UCDame3yw8cxBHpWVYU3nFAw",
      "text": "Damnn 4392 views! Good job!",
      "likes": 0,
      "timestamp": 1608768000,
      "parent": "root",
      "is_reply": false
    },
    {
      "author": "@jacob9902",
      "author_id": "UCqICsCeD7jSIlftQT8glUnA",
      "text": "Cool",
      "likes": 2,
      "timestamp": 1703376000,
      "parent": "root",
      "is_reply": false
    },
    {
      "author": "@Ger_1089",
      "author_id": "UCEF3_qVqzMXKvXkB8HSGQhg",
      "text": "🙏",
      "likes": 0,
      "timestamp": 1671840000,
      "parent": "root",
      "is_reply": false
    },
    {
      "author": "@GaziAlif",
      "author_id": "UCrzFms1WV6L_e7mz2aETShQ",
      "text": "Here before it blows up 💥",
      "likes": 0,
      "timestamp": 1703376000,
      "parent": "root",
      "is_reply": false
    },
    {
      "author": "@SASHA24",
      "author_id": "UC2xb4xTuRNRkAaeP5QecLiA",
      "text": "Тоже искал  посмотреть самое не популярное видео 😅",
      "likes": 4,
      "timestamp": 1734998400,
      "parent": "root",
      "is_reply": false
    },
    {
      "author": "@ArsenalBlox",
      "author_id": "UCcknwPbpiVRfE2wrA3jWWdg",
      "text": "i love you MrBeast <3",
      "likes": 1,
      "timestamp": 1703376000,
      "parent": "root",
      "is_reply": false
    },
    {
      "author": "@Decorsclocks",
      "author_id": "UCh12RB6wU_5b6KOVUCEYBOA",
      "text": "Ive been here before this hits 1m",
      "likes": 3,
      "timestamp": 1703376000,
      "parent": "root",
      "is_reply": false
    },
    {
      "author": "@user-ci6ij5bi7t",
      "author_id": "UCkGoDQl-gPM4Uk-1MyXr76A",
      "text": "Amazinggameplay",
      "likes": 1,
      "timestamp": 1671840000,
      "parent": "root",
      "is_reply": false
    },
    {
      "author": "@CrystelliaAUS",
      "author_id": "UCJ3C-txcsVDX8CTaXHYmz2Q",
      "text": "I just ate a dog :O",
      "likes": 4,
      "timestamp": 1450915200,
      "parent": "root",
      "is_reply": false
    },
    {
      "author": "@silencedhope4964",
      "author_id": "UCe0w8lfCqPxZ-PNCEdIY0pA",
      "text": "Lol you so much better at this than me",
      "likes": 0,
      "timestamp": 1450915200,
      "parent": "root",
      "is_reply": false
    },
    {
      "author": "@Joffy",
      "author_id": "UCtAkV6vFvGIMzI5aGtWabxg",
      "text": "Hey Mr.Beast, can I be in the next rendition of this series? Thanks",
      "likes": 0,
      "timestamp": 1577145600,
      "parent": "root",
      "is_reply": false
    },
    {
      "author": "@kacang_lantak3095",
      "author_id": "UCmGK3FVYDHs02lIDPd8eA0A",
      "text": "i love mrbeast😊",
      "likes": 0,
      "timestamp": 1577145600,
      "parent": "root",
      "is_reply": false
    },
    {
      "author": "@nikolang8791",
      "author_id": "UCkouFlQttE5hw92GlKdX0TQ",
      "text": "Look at his progress he’s made his videos now make millions of views",
      "likes": 2,
      "timestamp": 1577145600,
      "parent": "root",
      "is_reply": false
    },
    {
      "author": "@papagriff4402",
      "author_id": "UC8nruI46iHDliG3yKSUjGWg",
      "text": "Hi Legend 😊",
      "likes": 1,
      "timestamp": 1608768000,
      "parent": "root",
      "is_reply": false
    },
    {
      "author": "@soullessnesson1737",
      "author_id": "UCuZpd1rB2nlPo65eigjhEkg",
      "text": "👌",
      "likes": 0,
      "timestamp": 1671840000,
      "parent": "root",
      "is_reply": false
    },
    {
      "author": "@debruuuh3504",
      "author_id": "UC37bmIHY7jZWqHP5tRh1Ang",
      "text": "Day 5, episode 300 of Mr. Beast binge watch hihi ♡",
      "likes": 2,
      "timestamp": 1640304000,
      "parent": "root",
      "is_reply": false
    },
    {
      "author": "@زيادالشحادة-ز1د",
      "author_id": "UCclElEP2FtgGakI3z_tMvXA",
      "text": "انتي اليفضل",
      "likes": 1,
      "timestamp": 1671840000,
      "parent": "root",
      "is_reply": false
    },
    {
      "author": "@9KVN3",
      "author_id": "UCWtoHyxkUCqQczbN5jF_Tbg",
      "text": "7 years later 💯",
      "likes": 0,
      "timestamp": 1703376000,
      "parent": "root",
      "is_reply": false
    },
    {
      "author": "@Desertlover41552",
      "author_id": "UCple4NUEGp7aijzv5bKGR8w",
      "text": "Can I get a shoutout?",
      "likes": 4,
      "timestamp": 1671840000,
      "parent": "root",
      "is_reply": false
    },
    {
      "author": "@Vanvannie0617",
      "author_id": "UC663fT7x_zVmMu1x5QQr9YA",
      "text": "💝",
      "likes": 0,
      "timestamp": 1671840000,
      "parent": "root",
      "is_reply": false
    },
    {
      "author": "@ayushkanyal3163",
      "author_id": "UCdyLX-KV5NCrxHBlt837Vww",
      "text": "Woah",
      "likes": 0,
      "timestamp": 1703376000,
      "parent": "root",
      "is_reply": false
    },
    {
      "author": "@honeydofunny",
      "author_id": "UC5tjzxVil3BlEaWWd-PSEKA",
      "text": "Woah almost forgot to subscribe 😂",
      "likes": 0,
      "timestamp": 1671840000,
      "parent": "root",
      "is_reply": false
    },
    {
      "author": "@yepijow4215",
      "author_id": "UCWT8dXv7vTk_lX2PsoTO_uA",
      "text": "500 comment!",
      "likes": 3,
      "timestamp": 1703376000,
      "parent": "root",
      "is_reply": false
    },
    {
      "author": "@voidkarnage",
      "author_id": "UCm3m7A4Mlb_oSVM7r8r7rEQ",
      "text": "Thanks for the shoutout",
      "likes": 0,
      "timestamp": 1753315200,
      "parent": "root",
      "is_reply": false
    },
    {
      "author": "@mr-rm6fd",
      "author_id": "UC0wPqGdiIRh1--ASnQba_XA",
      "text": "Я с 2022",
      "likes": 2,
      "timestamp": 1671840000,
      "parent": "root",
      "is_reply": false
    },
    {
      "author": "@RedstoneMiner18",
      "author_id": "UCb9ZgXR1nu_c11gha_Diucg",
      "text": "Here from timeworks",
      "likes": 1,
      "timestamp": 1703376000,
      "parent": "root",
      "is_reply": false
    },
    {
      "author": "@ROMELGUN",
      "author_id": "UCbI3468SjNPYsOmBEEdoUHQ",
      "text": "My mission is to comment every videos on your channel 😊🤠☺️😊☺️",
      "likes": 0,
      "timestamp": 1671840000,
      "parent": "root",
      "is_reply": false
    },
    {
      "author": "@cheese2412",
      "author_id": "UCnHwVzQCv5jNzvH7keMReeQ",
      "text": "Insane vid lol",
      "likes": 0,
      "timestamp": 1703376000,
      "parent": "root",
      "is_reply": false
    },
    {
      "author": "@smol_comet",
      "author_id": "UCmye6XnxE8Q3qO-Pz9O8t4A",
      "text": "mrbeast least viewed",
      "likes": 5,
      "timestamp": 1671840000,
      "parent": "root",
      "is_reply": false
    },
    {
      "author": "@Titannnn399",
      "author_id": "UCTmw0AfBw1NjdzzCWeGVfmQ",
      "text": "Bro let out his inner 6000",
      "likes": 0,
      "timestamp": 1703376000,
      "parent": "root",
      "is_reply": false
    },
    {
      "author": "@fos9876",
      "author_id": "UCTivr_cUaKQBqmQcUI5qo5w",
      "text": "Before 30k",
      "likes": 0,
      "timestamp": 1703376000,
      "parent": "root",
      "is_reply": false
    },
    {
      "author": "@2cousinsplay650",
      "author_id": "UCwWvVmEtSlTQIALy4VbvylQ",
      "text": "How are u doing",
      "likes": 7,
      "timestamp": 1450915200,
      "parent": "root",
      "is_reply": false
    },
    {
      "author": "@JarGamesYT",
      "author_id": "UCZs3U5LWmfoTqlE4OvXwY7A",
      "text": "Im here before 30k",
      "likes": 0,
      "timestamp": 1703376000,
      "parent": "root",
      "is_reply": false
    },
    {
      "author": "@dermilitantefleischfresser",
      "author_id": "UCgVD8L5SX80ixDss4fp-X5g",
      "text": "I was here",
      "likes": 1,
      "timestamp": 1703376000,
      "parent": "root",
      "is_reply": false
    },
    {
      "author": "@darmalampung2indonesiaruss667",
      "author_id": "UCJpzuvwCZE4raeBEASjZgvg",
      "text": "Before 500 comment",
      "likes": 1,
      "timestamp": 1703376000,
      "parent": "root",
      "is_reply": false
    },
    {
      "author": "@hehe5523",
      "author_id": "UCFxPOaOU6MxO2G32-BpvzjA",
      "text": "Are you serious right now bro🎃",
      "likes": 2,
      "timestamp": 1671840000,
      "parent": "root",
      "is_reply": false
    },
    {
      "author": "@PratikBastola-m6w5g",
      "author_id": "UCwUZdh4Hgzn6FnwdASRB2yQ",
      "text": "The journey of hard work 😊 .",
      "likes": 0,
      "timestamp": 1748044800,
      "parent": "root",
      "is_reply": false
    },
    {
      "author": "@lucaiscoolyayakagamecentra7756",
      "author_id": "UCvPcYXsHl7sM2EhtALBLj2Q",
      "text": "❤❤❤❤",
      "likes": 0,
      "timestamp": 1734998400,
      "parent": "root",
      "is_reply": false
    },
    {
      "author": "@エレキング-s3f",
      "author_id": "UCwDNOg249j3ADlTn2ZXLf6A",
      "text": "good",
      "likes": 0,
      "timestamp": 1671840000,
      "parent": "root",
      "is_reply": false
    },
    {
      "author": "@SabitTSDM07",
      "author_id": "UC9CKra-60-M7YYgccJ7GCxg",
      "text": "Here before 500 comments and 35K views.",
      "likes": 2,
      "timestamp": 1703376000,
      "parent": "root",
      "is_reply": false
    },
    {
      "author": "@こいこいたたた",
      "author_id": "UCeKkT6Tjpj3wC-ScEvu-t5Q",
      "text": "伝説の始まり。",
      "likes": 1,
      "timestamp": 1703376000,
      "parent": "root",
      "is_reply": false
    },
    {
      "author": "@vineetsinghpatel7949",
      "author_id": "UCX-hNtuDLAEnZJno7C7PrmQ",
      "text": "Here before 450 comment",
      "likes": 1,
      "timestamp": 1703376000,
      "parent": "root",
      "is_reply": false
    },
    {
      "author": "@Randomedits36174",
      "author_id": "UCnNtCb0l6F9QFGbI82qZujw",
      "text": "Best youtuber everrrrr",
      "likes": 0,
      "timestamp": 1703376000,
      "parent": "root",
      "is_reply": false
    },
    {
      "author": "@crational3890",
      "author_id": "UCR6QSlYQufYUS8xeq31nEzA",
      "text": "woah",
      "likes": 0,
      "timestamp": 1734998400,
      "parent": "root",
      "is_reply": false
    },
    {
      "author": "@kingsplayroom9746",
      "author_id": "UCUxvT-zxbU9u2rJ0JEiRdMg",
      "text": "Well, if that's what u have to do I think I win XD",
      "likes": 0,
      "timestamp": 1608768000,
      "parent": "root",
      "is_reply": false
    },
    {
      "author": "@avionicme",
      "author_id": "UCRfeG6K75AMVQocVuN9nRlg",
      "text": "damn",
      "likes": 0,
      "timestamp": 1671840000,
      "parent": "root",
      "is_reply": false
    },
    {
      "author": "@Zura-h6k",
      "author_id": "UC-md-KZ_dwsXaFCtrZkklUg",
      "text": "8 years ago oh my God",
      "likes": 0,
      "timestamp": 1734998400,
      "parent": "root",
      "is_reply": false
    },
    {
      "author": "@Keedarchives",
      "author_id": "UCrfcIXDKfm5Eww7sgw-LhmQ",
      "text": "Wow",
      "likes": 0,
      "timestamp": 1671840000,
      "parent": "root",
      "is_reply": false
    },
    {
      "author": "@sethoddvlogger1082",
      "author_id": "UCfxS_xqKX1y_5pq1h7O-QNg",
      "text": "Helllllo peoplessss",
      "likes": 0,
      "timestamp": 1545609600,
      "parent": "root",
      "is_reply": false
    },
    {
      "author": "@xD-bf9qz",
      "author_id": "UCjX7aDXs6T4kTnLpvf4GpTA",
      "text": "Привет Мистер Бист",
      "likes": 0,
      "timestamp": 1703376000,
      "parent": "root",
      "is_reply": false
    },
    {
      "author": "@manojchiropractor86",
      "author_id": "UCgc9Fw7HsA_plyp1lM_e66w",
      "text": "❤❤❤❤🎉🎉",
      "likes": 0,
      "timestamp": 1737676800,
      "parent": "root",
      "is_reply": false
    },
    {
      "author": "@ShishirAdhikari-q4q",
      "author_id": "UC67wCB52vjyLM0KpAka6szw",
      "text": "Love you Brother.❤ i am Bangladeshi",
      "likes": 0,
      "timestamp": 1750723200,
      "parent": "root",
      "is_reply": false
    },
    {
      "author": "@エレキング-s3f",
      "author_id": "UCwDNOg249j3ADlTn2ZXLf6A",
      "text": "great👍🍜",
      "likes": 0,
      "timestamp": 1671840000,
      "parent": "root",
      "is_reply": false
    },
    {
      "author": "@Vixostoria",
      "author_id": "UCIPNGy8dDEjjdnuuW5uxZ4Q",
      "text": "Heyyy 2k viewssss 2019",
      "likes": 1,
      "timestamp": 1577145600,
      "parent": "root",
      "is_reply": false
    },
    {
      "author": "@lawsonzepponi1023",
      "author_id": "UCsj_llhRkzlftTHa8Y2VGVA",
      "text": "I wanna win lol",
      "likes": 1,
      "timestamp": 1450915200,
      "parent": "root",
      "is_reply": false
    },
    {
      "author": "@SalaarSiddiqui2009",
      "author_id": "UCL5-LVX8Ds-MRV_4dQ4g4Zg",
      "text": "here before 500",
      "likes": 0,
      "timestamp": 1703376000,
      "parent": "root",
      "is_reply": false
    },
    {
      "author": "@centlihankdennis2378",
      "author_id": "UCKSLSfU_wjn0__95lMc0brw",
      "text": "Hi Mrbeast num327",
      "likes": 0,
      "timestamp": 1608768000,
      "parent": "root",
      "is_reply": false
    },
    {
      "author": "@Blucario90",
      "author_id": "UCq8RiwZY38sAGoyBxRCv4TQ",
      "text": "you do not know how many times ive gotten comments asking for this shit",
      "likes": 1,
      "timestamp": 1514073600,
      "parent": "root",
      "is_reply": false
    },
    {
      "author": "@iwaswolfypro",
      "author_id": "UCykQBl4u5jKoRcCecI-0_kw",
      "text": "Ayy:))",
      "likes": 0,
      "timestamp": 1703376000,
      "parent": "root",
      "is_reply": false
    },
    {
      "author": "@venicerizza",
      "author_id": "UCo7B3LHwskCFCcVeB54wJ-A",
      "text": "15th ❤️",
      "likes": 0,
      "timestamp": 1608768000,
      "parent": "root",
      "is_reply": false
    },
    {
      "author": "@swggymeow6057",
      "author_id": "UCLpQHiMx-_iuzkKHpie-P7A",
      "text": "im surprised how this doesn’t have more than 1m views",
      "likes": 15,
      "timestamp": 1671840000,
      "parent": "root",
      "is_reply": false
    },
    {
      "author": "@lucky_lol",
      "author_id": "UClKBCvmAI0itKmul2oG_b7Q",
      "text": "Bro it feels weird omg",
      "likes": 0,
      "timestamp": 1703376000,
      "parent": "root",
      "is_reply": false
    },
    {
      "author": "@Doginthesleep",
      "author_id": "UCgWBQlGn10NoHVC0qKclnJQ",
      "text": "Op. Oooooop. 117th comment again. 🤪 I really should have been counting these...",
      "likes": 0,
      "timestamp": 1608768000,
      "parent": "root",
      "is_reply": false
    },
    {
      "author": "@ShonenSauce",
      "author_id": "UChiWZZI7gRZzug2zirmk1Jg",
      "text": "2 subscribers holy shit put me in :0",
      "likes": 4,
      "timestamp": 1450915200,
      "parent": "root",
      "is_reply": false
    },
    {
      "author": "@holasoywinston",
      "author_id": "UCcqY9O0Me5nvXhJFAkbOhGQ",
      "text": "Who is here in july 19 2022",
      "likes": 2,
      "timestamp": 1671840000,
      "parent": "root",
      "is_reply": false
    },
    {
      "author": "@chaircoal2590",
      "author_id": "UCrNxGRhJcKDosd4hjWU0JRQ",
      "text": "YOOOOOO MRBEAST",
      "likes": 0,
      "timestamp": 1640304000,
      "parent": "root",
      "is_reply": false
    },
    {
      "author": "@incog0956",
      "author_id": "UCCf5Hf8EvKlcvO0-AE1OZqA",
      "text": "What about this but in 2019?🤔",
      "likes": 0,
      "timestamp": 1577145600,
      "parent": "root",
      "is_reply": false
    },
    {
      "author": "@ГерманЗолкин-г3е",
      "author_id": "UCLdFxM8TnARDhefx7DH_txg",
      "text": "GG",
      "likes": 0,
      "timestamp": 1703376000,
      "parent": "root",
      "is_reply": false
    },
    {
      "author": "@Doginthesleep",
      "author_id": "UCgWBQlGn10NoHVC0qKclnJQ",
      "text": "I haven’t gotten to the point of shout-out Sunday’s 🤣 hopefully never will lol \nAlso, definitely don’t kill dogs 🐕 \n\n1/3 I lost RPS 🙁",
      "likes": 0,
      "timestamp": 1608768000,
      "parent": "root",
      "is_reply": false
    },
    {
      "author": "@FreeSpiritPaulette",
      "author_id": "UC6moxqX_MROdJPp8xHloeoA",
      "text": "Hello mrbeast \n\nEdit: here before 30k views",
      "likes": 1,
      "timestamp": 1703376000,
      "parent": "root",
      "is_reply": false
    },
    {
      "author": "@loxth7354",
      "author_id": "UCEO--v86vquHjN_ZkZ8DzLQ",
      "text": "😍😍",
      "likes": 0,
      "timestamp": 1734998400,
      "parent": "root",
      "is_reply": false
    },
    {
      "author": "@superr7776",
      "author_id": "UCV_m7jyLhf8a5iwnFpA_iVA",
      "text": "Me next",
      "likes": 0,
      "timestamp": 1671840000,
      "parent": "root",
      "is_reply": false
    },
    {
      "author": "@RandytheRedneck",
      "author_id": "UCdUbQFtkjhO7w7lPM_owpdg",
      "text": "🙂",
      "likes": 0,
      "timestamp": 1671840000,
      "parent": "root",
      "is_reply": false
    },
    {
      "author": "@MeatandTatersGaming54",
      "author_id": "UChbkL-ZuHcafOFNgxBZ42dw",
      "text": "LMAO!!! love it",
      "likes": 6,
      "timestamp": 1450915200,
      "parent": "root",
      "is_reply": false
    },
    {
      "author": "@СашаПро-ъ1ю",
      "author_id": "UCwNlKIIhR0xGdrl8MYcTcyQ",
      "text": "Привет",
      "likes": 0,
      "timestamp": 1703376000,
      "parent": "root",
      "is_reply": false
    },
    {
      "author": "@AmongUs-vj1ew",
      "author_id": "UCQ1cV4hqV_8bIUjGPsjkflQ",
      "text": "You should shout me out next Sunday fr",
      "likes": 1,
      "timestamp": 1750723200,
      "parent": "root",
      "is_reply": false
    },
    {
      "author": "@Fjnzmjsjwjeurh",
      "author_id": "UCsN7jAqTvz58txahBZfzmgA",
      "text": "Yo",
      "likes": 1,
      "timestamp": 1703376000,
      "parent": "root",
      "is_reply": false
    },
    {
      "author": "@Whobilly",
      "author_id": "UC451PIF8rykIfv0X37Gr6PQ",
      "text": "Lmao",
      "likes": 3,
      "timestamp": 1450915200,
      "parent": "root",
      "is_reply": false
    },
    {
      "author": "@Shayan2027",
      "author_id": "UCxKAOkqmA6zdWXLLYjspKiw",
      "text": "First person in 5hrs 😲😲",
      "likes": 1,
      "timestamp": 1734998400,
      "parent": "root",
      "is_reply": false
    },
    {
      "author": "@heitor7533",
      "author_id": "UCWmg_gVvQewU-p_PXLZuZKw",
      "text": "Cade os BR daqui?",
      "likes": 2,
      "timestamp": 1753315200,
      "parent": "root",
      "is_reply": false
    },
    {
      "author": "@joshuakim1497",
      "author_id": "UCPyXnOujlJunzBnquTY9qlw",
      "text": "Lol do you check these anymore",
      "likes": 1,
      "timestamp": 1640304000,
      "parent": "root",
      "is_reply": false
    },
    {
      "author": "@كراراحمد-ع6ظ9ف",
      "author_id": "UCxnINz8lB77XimEJSosuvZA",
      "text": "ماهذا يا مستر بيست",
      "likes": 1,
      "timestamp": 1671840000,
      "parent": "root",
      "is_reply": false
    },
    {
      "author": "@coopertmc1101",
      "author_id": "UC76V--ouwzKgrHpuNtGCMNA",
      "text": "This aged well",
      "likes": 0,
      "timestamp": 1703376000,
      "parent": "root",
      "is_reply": false
    },
    {
      "author": "@Deioww",
      "author_id": "UCxw8fWFc1WGXobCrqaUfQew",
      "text": "Six years ago..",
      "likes": 0,
      "timestamp": 1671840000,
      "parent": "root",
      "is_reply": false
    },
    {
      "author": "@endlessmike5027",
      "author_id": "UCygeEoG2-Dp0qb2O4ySIMrQ",
      "text": "I think I deserve a shoutout next Sunday because I subscribed to everyone in the video and liked all their vids, and I am new to youtube, and I killed 2 bears and not squirrels. \n\n\n\n\n\n\n\n\n\n\n\n\n\nI also upload minecraft vids😂😜",
      "likes": 1,
      "timestamp": 1450915200,
      "parent": "root",
      "is_reply": false
    },
    {
      "author": "@garypena8260",
      "author_id": "UCSmTFce5v44Elu5PzfUGS3A",
      "text": "Hi",
      "likes": 0,
      "timestamp": 1545609600,
      "parent": "root",
      "is_reply": false
    },
    {
      "author": "@sasmitagouda7780",
      "author_id": "UCqbnyIg4bnaPO7Hc3JAaRMg",
      "text": "Who is here in July 20 2022",
      "likes": 3,
      "timestamp": 1671840000,
      "parent": "root",
      "is_reply": false
    },
    {
      "author": "@Spiceman_TheFakest",
      "author_id": "UCbonZDV_s9Rl_YGvUFHSaig",
      "text": "here before 500 comments",
      "likes": 0,
      "timestamp": 1703376000,
      "parent": "root",
      "is_reply": false
    },
    {
      "author": "@aussielegend2131",
      "author_id": "UCe-7i-A6LtPQyuce2gwGvCQ",
      "text": "Hey boomets",
      "likes": 1,
      "timestamp": 1608768000,
      "parent": "root",
      "is_reply": false
    },
    {
      "author": "@rodrigoramos465",
      "author_id": "UCspx43KZK3WtSSGpeGRP-hg",
      "text": "vamos encontre el video menos vidal de mrBeast",
      "likes": 0,
      "timestamp": 1734998400,
      "parent": "root",
      "is_reply": false
    },
    {
      "author": "@degouw",
      "author_id": "UCCHWT4GM3TATFP_8Um_bVgA",
      "text": "make a gameplay vid",
      "likes": 0,
      "timestamp": 1608768000,
      "parent": "root",
      "is_reply": false
    },
    {
      "author": "@rolexkutty",
      "author_id": "UCkpuzciGNX3T4qEyf5p_s-Q",
      "text": "i was here on 454 comments",
      "likes": 0,
      "timestamp": 1703376000,
      "parent": "root",
      "is_reply": false
    },
    {
      "author": "@dylanhopkins5743",
      "author_id": "UCNteoAMX1i3q5N3Yocdg55A",
      "text": "Dz the fs hi",
      "likes": 1,
      "timestamp": 1450915200,
      "parent": "root",
      "is_reply": false
    },
    {
      "author": "@christian1893",
      "author_id": "UCdtA2tDi8iw28TjC6vfZVgA",
      "text": "Un capo el mr beast",
      "likes": 0,
      "timestamp": 1671840000,
      "parent": "root",
      "is_reply": false
    },
    {
      "author": "@cinqtonic",
      "author_id": "UC--Y_iXGj7YsrIiYsYZjiBg",
      "text": "Some guy commented this shit on my video (and of course thanks to YouTubes bots, it went to the spam comments folder thankfully lol). And he was doing the EXACT same shit as what you said in your video lol. Its so annoying",
      "likes": 2,
      "timestamp": 1450915200,
      "parent": "root",
      "is_reply": false
    },
    {
      "author": "@hvelez4646",
      "author_id": "UCo83Olss6d5uRyyMKEkctVg",
      "text": "shout out",
      "likes": 0,
      "timestamp": 1671840000,
      "parent": "root",
      "is_reply": false
    },
    {
      "author": "@AuraOP",
      "author_id": "UC8IWBfamcvspu4W8hDsgyig",
      "text": "deez nutz fr",
      "likes": 0,
      "timestamp": 1703376000,
      "parent": "root",
      "is_reply": false
    },
    {
      "author": "@rein.269",
      "author_id": "UCgcrgd30Z3TJL3jLy-i0UiQ",
      "text": "Shoutout to US Playz that's me",
      "likes": 0,
      "timestamp": 1671840000,
      "parent": "root",
      "is_reply": false
    },
    {
      "author": "@slount",
      "author_id": "UC882BYL_L-FWZq1UVa4CgoA",
      "text": "59,064 view",
      "likes": 2,
      "timestamp": 1758672000,
      "parent": "root",
      "is_reply": false
    },
    {
      "author": "@dezyezy2157",
      "author_id": "UCa-pZIwkkqc8nIin0zXAfdg",
      "text": "Mrbeast rarest vid",
      "likes": 0,
      "timestamp": 1608768000,
      "parent": "root",
      "is_reply": false
    },
    {
      "author": "@heyitsmarcelo5705",
      "author_id": "UCKYMnpl4cMPIfQOF5DBfZbQ",
      "text": "Hey I would love a shoutout",
      "likes": 0,
      "timestamp": 1608768000,
      "parent": "root",
      "is_reply": false
    },
    {
      "author": "@sunshine_bypolar8769",
      "author_id": "UC-M1KiB4EE4FUOs4J8cS7Ug",
      "text": "Lol 😂",
      "likes": 0,
      "timestamp": 1640304000,
      "parent": "root",
      "is_reply": false
    },
    {
      "author": "@No_namess",
      "author_id": "UC4wUbN1C8CQrcszp5zzaUOQ",
      "text": "😂",
      "likes": 1,
      "timestamp": 1703376000,
      "parent": "root",
      "is_reply": false
    },
    {
      "author": "@VizzyYTSubscribe",
      "author_id": "UCtEM7wEa2HRPzJd6SVxZZLg",
      "text": "lol",
      "likes": 0,
      "timestamp": 1450915200,
      "parent": "root",
      "is_reply": false
    },
    {
      "author": "@aydacho3",
      "author_id": "UCA1QgBiwxlLSIIDmlr0VWWg",
      "text": "yoo wt",
      "likes": 2,
      "timestamp": 1703376000,
      "parent": "root",
      "is_reply": false
    },
    {
      "author": "@smfreeze9198",
      "author_id": "UCCI2eZxPca1ShcZUTvAhmFw",
      "text": "May I have a shout out",
      "likes": 0,
      "timestamp": 1577145600,
      "parent": "root",
      "is_reply": false
    },
    {
      "author": "@BraggiBlender",
      "author_id": "UCDZr4_NvASZz-6zHn2DwmDw",
      "text": "Fuck, already sold my soul.",
      "likes": 1,
      "timestamp": 1450915200,
      "parent": "root",
      "is_reply": false
    },
    {
      "author": "@hayden_6331",
      "author_id": "UCoZz2gbe-prA45-SPC8L7gQ",
      "text": "yoooo im early",
      "likes": 0,
      "timestamp": 1703376000,
      "parent": "root",
      "is_reply": false
    },
    {
      "author": "@imacutecatt",
      "author_id": "UCd8ofrdUgIEJbegXosYEl4Q",
      "text": "lol so little views",
      "likes": 3,
      "timestamp": 1703376000,
      "parent": "root",
      "is_reply": false
    },
    {
      "author": "@DaggerMan-ov1vf",
      "author_id": "UC5b5CG-ok0WdpQYW3V2VAiQ",
      "text": "I’m here before 30k!",
      "likes": 0,
      "timestamp": 1703376000,
      "parent": "root",
      "is_reply": false
    },
    {
      "author": "@unknow61010",
      "author_id": "UC3s7QxGRvHpuwtX4uwlyihQ",
      "text": "bro the un views ever in mr beast and now 134m subscribe",
      "likes": 1,
      "timestamp": 1703376000,
      "parent": "root",
      "is_reply": false
    },
    {
      "author": "@TheBlackArchive-q2k",
      "author_id": "UCfjNk-SLF108fYETcQAKw4w",
      "text": "OooooooooooooOoOOOOOoOOOOOoOoOOOOOOOO",
      "likes": 0,
      "timestamp": 1671840000,
      "parent": "root",
      "is_reply": false
    },
    {
      "author": "@aryanadi1357",
      "author_id": "UCyZERmBY9iJVmJRKBN_hVIQ",
      "text": "Fok!",
      "likes": 0,
      "timestamp": 1640304000,
      "parent": "root",
      "is_reply": false
    },
    {
      "author": "@BsdXzaney",
      "author_id": "UCEveAgE6HceR0zJffU4rWTA",
      "text": "I WAS HERE BEFORE THIS BLOWS UP!!!",
      "likes": 0,
      "timestamp": 1703376000,
      "parent": "root",
      "is_reply": false
    },
    {
      "author": "@DarkClouddd",
      "author_id": "UCErscFF9Uc6uaAybRwP965w",
      "text": "Sell your soul seems legit",
      "likes": 0,
      "timestamp": 1450915200,
      "parent": "root",
      "is_reply": false
    },
    {
      "author": "@LlLTMAN",
      "author_id": "UCWWxP_ag13g8hs-Zb8aikcQ",
      "text": "This is his least popular upload wow",
      "likes": 2,
      "timestamp": 1671840000,
      "parent": "root",
      "is_reply": false
    },
    {
      "author": "@Midoche",
      "author_id": "UCv6gqE1cK8hFzSdI1dCaX-g",
      "text": "56K only? Omg",
      "likes": 0,
      "timestamp": 1748044800,
      "parent": "root",
      "is_reply": false
    },
    {
      "author": "@Romulo1259",
      "author_id": "UCwP5huyCSwt60M4BNr2dfTg",
      "text": "Before 500 comments",
      "likes": 0,
      "timestamp": 1703376000,
      "parent": "root",
      "is_reply": false
    },
    {
      "author": "@RyderB",
      "author_id": "UCd3GK4Es4EoAtf8jKIpRPWA",
      "text": "before this vid blows up",
      "likes": 0,
      "timestamp": 1703376000,
      "parent": "root",
      "is_reply": false
    },
    {
      "author": "@melaniehanson2303",
      "author_id": "UCTXFgEJpvzTW1XaqSX4GD-Q",
      "text": "2021 anyone?????",
      "likes": 0,
      "timestamp": 1640304000,
      "parent": "root",
      "is_reply": false
    },
    {
      "author": "@king18888boss",
      "author_id": "UCE-JgNuMKyKSbkHgtXTgXZA",
      "text": "nice views",
      "likes": 1,
      "timestamp": 1577145600,
      "parent": "root",
      "is_reply": false
    },
    {
      "author": "@user-gm7sw3nv7p",
      "author_id": "UCtYKCFwDluSMX1FJ14a4HdA",
      "text": "306❤",
      "likes": 0,
      "timestamp": 1703376000,
      "parent": "root",
      "is_reply": false
    },
    {
      "author": "@BROEATBREAD",
      "author_id": "UCfrKS0WbfMLgt1f94GhEBUg",
      "text": "Where’s my sub?",
      "likes": 1,
      "timestamp": 1640304000,
      "parent": "root",
      "is_reply": false
    },
    {
      "author": "@AKPOWER",
      "author_id": "UC5HIbpphbVNSHuX0CAIA9SQ",
      "text": "shout out days ruined my channel lol. I got a bunch of subs but no one stayed after they got their shoutout and i was left with a bunch of subs but no views.",
      "likes": 1,
      "timestamp": 1450915200,
      "parent": "root",
      "is_reply": false
    },
    {
      "author": "@aoubayd562",
      "author_id": "UCea4RZa7tgguoDnAZkdn8YA",
      "text": "Mr beast the best",
      "likes": 0,
      "timestamp": 1703376000,
      "parent": "root",
      "is_reply": false
    },
    {
      "author": "@ultraduckking",
      "author_id": "UCDu09L8fkr8Z0AHNUbjxhVQ",
      "text": "288th!",
      "likes": 0,
      "timestamp": 1671840000,
      "parent": "root",
      "is_reply": false
    },
    {
      "author": "@Zitly.",
      "author_id": "UCA2B7F8-EaDwkSrij8t4J6A",
      "text": "Today’s Sunday next with",
      "likes": 0,
      "timestamp": 1753315200,
      "parent": "root",
      "is_reply": false
    },
    {
      "author": "@SouptikGanguly-ew6jt",
      "author_id": "UC32m5g1qFkzWHFbwznFKG1w",
      "text": "Hehe",
      "likes": 0,
      "timestamp": 1742774400,
      "parent": "root",
      "is_reply": false
    },
    {
      "author": "@ku8ooo",
      "author_id": "UCQJwqfdaSPfVASt-Uvw-iAQ",
      "text": "Most unpopular vid of mrbeast",
      "likes": 1,
      "timestamp": 1734998400,
      "parent": "root",
      "is_reply": false
    },
    {
      "author": "@therealevsauce",
      "author_id": "UCfRRR24leNMYxzyvbdhtwzA",
      "text": "LMAO",
      "likes": 0,
      "timestamp": 1671840000,
      "parent": "root",
      "is_reply": false
    },
    {
      "author": "@mastapasta2",
      "author_id": "UChyv7mNbSr2arUYTD-TjBqw",
      "text": "1 year since last commentia wow",
      "likes": 1,
      "timestamp": 1745452800,
      "parent": "root",
      "is_reply": false
    },
    {
      "author": "@tienat3852",
      "author_id": "UCnU7uoC6VtGE3D-Qhk3wqyw",
      "text": "Hello đây là video thứ 308 ❤❤❤\n2/1/2025",
      "likes": 2,
      "timestamp": 1737676800,
      "parent": "root",
      "is_reply": false
    },
    {
      "author": "@s1mpolzz",
      "author_id": "UCvYj4lShWZdLK3xvI5zjB_w",
      "text": "First person in 1h",
      "likes": 0,
      "timestamp": 1734998400,
      "parent": "root",
      "is_reply": false
    },
    {
      "author": "@AzureV2_legacy",
      "author_id": "UCTk_xYVba33x3kT6y01QgUQ",
      "text": "least viewed MrBeast video\nI was here",
      "likes": 0,
      "timestamp": 1734998400,
      "parent": "root",
      "is_reply": false
    },
    {
      "author": "@rafidhasan2752",
      "author_id": "UCK7PX76Vr5yLER5qV4IgCNA",
      "text": "21k lol",
      "likes": 0,
      "timestamp": 1671840000,
      "parent": "root",
      "is_reply": false
    },
    {
      "author": "@WetRanch",
      "author_id": "UCx8I7HY3CxZOCiPkT0h3xQw",
      "text": "me pls",
      "likes": 1,
      "timestamp": 1450915200,
      "parent": "root",
      "is_reply": false
    },
    {
      "author": "@Ionley",
      "author_id": "UCPR__568t7fYZhCwH-hgOqQ",
      "text": "Shout me out Jimmy 🤣",
      "likes": 0,
      "timestamp": 1608768000,
      "parent": "root",
      "is_reply": false
    },
    {
      "author": "@GavGaming15",
      "author_id": "UCA4t-vw9I27JlZU6RFw-YZQ",
      "text": "It’s Sunday Guys",
      "likes": 1,
      "timestamp": 1703376000,
      "parent": "root",
      "is_reply": false
    },
    {
      "author": "@JaysPremiumcontent",
      "author_id": "UC-QLh9KxbvI9LrSLZg81Eqg",
      "text": "13k views",
      "likes": 0,
      "timestamp": 1640304000,
      "parent": "root",
      "is_reply": false
    },
    {
      "author": "@lordbeerus3267",
      "author_id": "UC20l_rI0LV2XYLGH6xaVEEw",
      "text": "69,420",
      "likes": 1,
      "timestamp": 1640304000,
      "parent": "root",
      "is_reply": false
    },
    {
      "author": "@cubicblue6655",
      "author_id": "UCTXhtS8eDUg2iOKqT6dYdIQ",
      "text": "snakesauce",
      "likes": 1,
      "timestamp": 1450915200,
      "parent": "root",
      "is_reply": false
    },
    {
      "author": "@FistLand",
      "author_id": "UCLVUBP75FdFepHvVxwEbRkw",
      "text": "Кто из 2024 года?",
      "likes": 2,
      "timestamp": 1734998400,
      "parent": "root",
      "is_reply": false
    },
    {
      "author": "@Ralot7",
      "author_id": "UCMbLe3FZFb7_gFh4s4Qxj1A",
      "text": "Did you have a ADHD attack during the last 30 seconds of the video?",
      "likes": 4,
      "timestamp": 1450915200,
      "parent": "root",
      "is_reply": false
    },
    {
      "author": "@danilka2405",
      "author_id": "UCG0Jkk8AeHeL-4sDA2QpPiA",
      "text": "дарова",
      "likes": 0,
      "timestamp": 1734998400,
      "parent": "root",
      "is_reply": false
    },
    {
      "author": "@alwaystrending9116",
      "author_id": "UCar2fpIkER0Q6_wM-ShTJkQ",
      "text": "I was here….",
      "likes": 0,
      "timestamp": 1671840000,
      "parent": "root",
      "is_reply": false
    },
    {
      "author": "@InternalSyraa",
      "author_id": "UCwzLvN3H9FxDSFbWb4sG-Pw",
      "text": "jejak",
      "likes": 0,
      "timestamp": 1745452800,
      "parent": "root",
      "is_reply": false
    },
    {
      "author": "@MrBobalob",
      "author_id": "UCUT0LTXoNMaO0-Sg8arpaBw",
      "text": "First person in 3 weeks",
      "likes": 0,
      "timestamp": 1734998400,
      "parent": "root",
      "is_reply": false
    },
    {
      "author": "@KevinWeb3",
      "author_id": "UCCPQE9NWEkwDxH4Re8RKK_w",
      "text": "Nice",
      "likes": 1,
      "timestamp": 1450915200,
      "parent": "root",
      "is_reply": false
    },
    {
      "author": "@danielparvin9083",
      "author_id": "UC3aT_mAbd62RusT9VldWfkQ",
      "text": "Most unviewed mr beast vireo",
      "likes": 2,
      "timestamp": 1671840000,
      "parent": "root",
      "is_reply": false
    },
    {
      "author": "@htyfg11",
      "author_id": "UCGfw28L87Myisp-0pZKcIfw",
      "text": "Mrbest",
      "likes": 0,
      "timestamp": 1703376000,
      "parent": "root",
      "is_reply": false
    },
    {
      "author": "@gonegyuiihhhthkjjr",
      "author_id": "UCLYjj1sa9TXnymLoyxTgVag",
      "text": "Mr beast",
      "likes": 0,
      "timestamp": 1703376000,
      "parent": "root",
      "is_reply": false
    },
    {
      "author": "@nagagutti8432",
      "author_id": "UCbH0hNpX_mIpAO80xGJQmSA",
      "text": "306",
      "likes": 0,
      "timestamp": 1640304000,
      "parent": "root",
      "is_reply": false
    },
    {
      "author": "@andreys6968",
      "author_id": "UC2w2lM1rW_GbsTpUTcCK7PQ",
      "text": ":oops:",
      "likes": 0,
      "timestamp": 1671840000,
      "parent": "root",
      "is_reply": false
    },
    {
      "author": "@crisreina4954",
      "author_id": "UCx4c0OQYaJcLxT_hDyNTkyg",
      "text": "❤❤❤",
      "likes": 0,
      "timestamp": 1734998400,
      "parent": "root",
      "is_reply": false
    },
    {
      "author": "@katiamurador",
      "author_id": "UCpT-Wlfh00-LWyB25vqfcwg",
      "text": "Here before 450 comments",
      "likes": 1,
      "timestamp": 1703376000,
      "parent": "root",
      "is_reply": false
    },
    {
      "author": "@yepijow4215",
      "author_id": "UCWT8dXv7vTk_lX2PsoTO_uA",
      "text": "Wow",
      "likes": 0,
      "timestamp": 1703376000,
      "parent": "root",
      "is_reply": false
    },
    {
      "author": "@playyarikyt6208",
      "author_id": "UC1-jpbMU_GVHntTJF1jDM6Q",
      "text": "Hello",
      "likes": 1,
      "timestamp": 1671840000,
      "parent": "root",
      "is_reply": false
    },
    {
      "author": "@srijal1",
      "author_id": "UCsFAIxNVF46iggB_zKLAyEw",
      "text": "Yo",
      "likes": 0,
      "timestamp": 1703376000,
      "parent": "root",
      "is_reply": false
    },
    {
      "author": "@Connorlo442",
      "author_id": "UCezj0j1AHDzsWTR6Z1_6Yeg",
      "text": "lol",
      "likes": 0,
      "timestamp": 1545609600,
      "parent": "root",
      "is_reply": false
    },
    {
      "author": "@threeamigos2848",
      "author_id": "UCHyv5dB99kxE5aCjCl_nSCQ",
      "text": "Here before 450 comments",
      "likes": 0,
      "timestamp": 1703376000,
      "parent": "root",
      "is_reply": false
    },
    {
      "author": "@JavierColindres151",
      "author_id": "UCnaWoqvjr5MXn7EdvnwvdGg",
      "text": "Hi",
      "likes": 0,
      "timestamp": 1703376000,
      "parent": "root",
      "is_reply": false
    },
    {
      "author": "@mmcherryblossom",
      "author_id": "UCDhAOOIYdXnHCgwjTbiH9tg",
      "text": "Hi",
      "likes": 1,
      "timestamp": 1703376000,
      "parent": "root",
      "is_reply": false
    },
    {
      "author": "@Jannatul89",
      "author_id": "UCNpZDZPX3lNiNZtIAMNImpg",
      "text": "Here before 450 comments",
      "likes": 0,
      "timestamp": 1703376000,
      "parent": "root",
      "is_reply": false
    },
    {
      "author": "@kagandemir448",
      "author_id": "UCJKS9rCSk3O7kCFmWxXlIkg",
      "text": "hi",
      "likes": 1,
      "timestamp": 1703376000,
      "parent": "root",
      "is_reply": false
    },
    {
      "author": "@--Samuel--",
      "author_id": "UCDkm4O-7Jr10jTvWk0LqtLA",
      "text": "Hello",
      "likes": 1,
      "timestamp": 1703376000,
      "parent": "root",
      "is_reply": false
    },
    {
      "author": "@WiktorBąk-b9h",
      "author_id": "UCWoIZiGJ-DLydXGsAMUlsug",
      "text": "Hi",
      "likes": 0,
      "timestamp": 1764720000,
      "parent": "root",
      "is_reply": false
    },
    {
      "author": "@Roworram",
      "author_id": "UCN2X9FnRKOcdXF__9mCX6SQ",
      "text": "Pen is",
      "likes": 0,
      "timestamp": 1671840000,
      "parent": "root",
      "is_reply": false
    },
    {
      "author": "@yepijow4215",
      "author_id": "UCWT8dXv7vTk_lX2PsoTO_uA",
      "text": "490",
      "likes": 0,
      "timestamp": 1703376000,
      "parent": "root",
      "is_reply": false
    },
    {
      "author": "@AlphaMC",
      "author_id": "UCczVGEKd7mlIaEenCdbH93w",
      "text": "ok can i have a shoutout 🥺",
      "likes": 0,
      "timestamp": 1640304000,
      "parent": "root",
      "is_reply": false
    },
    {
      "author": "@AIVideo7791",
      "author_id": "UCjGFiVPx6qTqSwq0BSkUPDg",
      "text": "Me 2012😊",
      "likes": 0,
      "timestamp": 1742774400,
      "parent": "root",
      "is_reply": false
    },
    {
      "author": "@SeanWL-VV",
      "author_id": "UCTS6gY3ExXA9y7rgNX6Jsdg",
      "text": "hi sub",
      "likes": 0,
      "timestamp": 1703376000,
      "parent": "root",
      "is_reply": false
    },
    {
      "author": "@user-fx3qu6un9z",
      "author_id": "UC_QtL89gI6ie-VTqrMR9fcQ",
      "text": "Suuuuuuuuuuper 🔥🔥🔥❤️❤️❤️🎈🎯🎆🍫🧁🧡🎇⚾💪🧨😘🛑💙🎨🚀😃🎊🎱👍🛩️🥎🍩⚽😉🎉❣️💛💛🍭🍭🎀🎀🏐🏐🏀🍰❤️🏈😃🎊🎱🎨👍👍🛑🎀🥎😘🥎🍩🍩💪⚽😉⚾⚾🎇🧡🧨🧁🧁🔥🛑💙💙🎨🎨🚀🎯🎈😃🎊🎱👍🏐🎀🍭🍭💛💛❣️🎉🎉😉⚽🧨🧨🧁🧁🧁🧁🧁🧁🧁🎨🎨🎨🎨🎨🎨🎨🎨🎆🎯🚀🎈🏈❤️❤️🍰🏀🏀🎱🚀🎆🎆🎱🎨💙🔥👍🏐🎀🛩️🛑🔥🎀🎀🍭🥎😘🧡🥎🍭💛🍩🧨🧡💪⚽❣️❣️🎉😉⚾🤎💪🧨🍩🍩🥎🥎🛩️🎨🎨🎨🎱🛩️🥎🥎💛❣️🎉😉⚽🍩🥎🛩️👍🏀🎱🍰❤️🏈😃🚀🎈🎯🎨💙👍🎱👍👍🛑🔥🎨🛑🔥🛑🍩🏐❤️❤️👍🎀💛❣️O",
      "likes": 0,
      "timestamp": 1671840000,
      "parent": "root",
      "is_reply": false
    },
    {
      "author": "@claygonzalez2335",
      "author_id": "UC05vB9cVPUYLZc8nY7bg8Vw",
      "text": "You guys don’t forget to subscribe",
      "likes": 0,
      "timestamp": 1640304000,
      "parent": "root",
      "is_reply": false
    },
    {
      "author": "@amos2811",
      "author_id": "UCNgE_uZ02kfUQtF_IFNgBLQ",
      "text": "Erster deutscher Kommentar",
      "likes": 0,
      "timestamp": 1608768000,
      "parent": "root",
      "is_reply": false
    },
    {
      "author": "@Inanutshell...",
      "author_id": "UCjMdyhqcuMEjOsYDzycnAtQ",
      "text": "Lok",
      "likes": 1,
      "timestamp": 1671840000,
      "parent": "root",
      "is_reply": false
    },
    {
      "author": "@JoanLeaf55",
      "author_id": "UCuPD9N3d4CZyV5IZmKDQz0g",
      "text": "Shooter game",
      "likes": 0,
      "timestamp": 1734998400,
      "parent": "root",
      "is_reply": false
    },
    {
      "author": "@Meccomouse",
      "author_id": "UC3AOp8wabPNCigKOR6sDnIg",
      "text": "Only 30k views?",
      "likes": 0,
      "timestamp": 1703376000,
      "parent": "root",
      "is_reply": false
    },
    {
      "author": "@srijal1",
      "author_id": "UCsFAIxNVF46iggB_zKLAyEw",
      "text": "In 30k views",
      "likes": 0,
      "timestamp": 1703376000,
      "parent": "root",
      "is_reply": false
    },
    {
      "author": "@OTC_ACE",
      "author_id": "UCGyz3ZdKsYUhQuNPnLEGfEw",
      "text": "Where is my shout out lmao",
      "likes": 0,
      "timestamp": 1640304000,
      "parent": "root",
      "is_reply": false
    },
    {
      "author": "@Fizzie_Fiend",
      "author_id": "UCsjMIOekJ4zuoaZAIdy0b5Q",
      "text": "Who else scrolled though his entire selection of most popular videos just to find his least popular one of all time?",
      "likes": 2,
      "timestamp": 1671840000,
      "parent": "root",
      "is_reply": false
    },
    {
      "author": "@yepijow4215",
      "author_id": "UCWT8dXv7vTk_lX2PsoTO_uA",
      "text": "584",
      "likes": 0,
      "timestamp": 1703376000,
      "parent": "root",
      "is_reply": false
    },
    {
      "author": "@jaydostomps2313",
      "author_id": "UCHKuym2m5gQLsPqop09vNVA",
      "text": "Can I get a shout out lol",
      "likes": 0,
      "timestamp": 1640304000,
      "parent": "root",
      "is_reply": false
    },
    {
      "author": "@nileellenbandola5776",
      "author_id": "UCU7vJf7fpn1quRZmZFUyTmA",
      "text": "This is one of his least viewed videos on his channel and he had more then 60 m now and this is 13k lower then my most viewed vid",
      "likes": 0,
      "timestamp": 1640304000,
      "parent": "root",
      "is_reply": false
    },
    {
      "author": "@yepijow4215",
      "author_id": "UCWT8dXv7vTk_lX2PsoTO_uA",
      "text": "497",
      "likes": 0,
      "timestamp": 1703376000,
      "parent": "root",
      "is_reply": false
    },
    {
      "author": "@voidalicia1196",
      "author_id": "UCL7G63Z6mGxKeGCCIffDPmw",
      "text": "give shoutout",
      "likes": 0,
      "timestamp": 1640304000,
      "parent": "root",
      "is_reply": false
    },
    {
      "author": "@648546lllooolll",
      "author_id": "UCbuA6-HOHA-0VVPCrsDOjuA",
      "text": "I'd do ANYTHING just to hang out with these guys for a day.!!",
      "likes": 16,
      "timestamp": 1640304000,
      "parent": "root",
      "is_reply": false
    },
    {
      "author": "@Temerityofficial21201",
      "author_id": "UCr-zkaTMk06-pqH2rx9sJHw",
      "text": "Who’s from Timeworks 🖐️",
      "likes": 1,
      "timestamp": 1703376000,
      "parent": "root",
      "is_reply": false
    },
    {
      "author": "@Yenexs1788",
      "author_id": "UC6Fxpb6IO8ZJSeXwHcRyAEQ",
      "text": "I Have a Wish...",
      "likes": 0,
      "timestamp": 1734998400,
      "parent": "root",
      "is_reply": false
    },
    {
      "author": "@dhruvhimatsingka3965",
      "author_id": "UCbno1LRcsj_uo-FcRoo3QFw",
      "text": "only 9.8k views",
      "likes": 0,
      "timestamp": 1640304000,
      "parent": "root",
      "is_reply": false
    },
    {
      "author": "@lucky_lol",
      "author_id": "UClKBCvmAI0itKmul2oG_b7Q",
      "text": "Will you still give me shoutout",
      "likes": 1,
      "timestamp": 1703376000,
      "parent": "root",
      "is_reply": false
    },
    {
      "author": "@dip3244",
      "author_id": "UCZDiE_9ch3NuGDAq5PsYEPg",
      "text": "shout out plz",
      "likes": 0,
      "timestamp": 1671840000,
      "parent": "root",
      "is_reply": false
    },
    {
      "author": "@yepijow4215",
      "author_id": "UCWT8dXv7vTk_lX2PsoTO_uA",
      "text": "492",
      "likes": 0,
      "timestamp": 1703376000,
      "parent": "root",
      "is_reply": false
    },
    {
      "author": "@mobwhispererMC",
      "author_id": "UCFb-7s3LTRNk5-Xsw6IccFA",
      "text": "HI",
      "likes": 3,
      "timestamp": 1450915200,
      "parent": "root",
      "is_reply": false
    },
    {
      "author": "@mainhandle101",
      "author_id": "UChRQ2tz9JLedS59tvm3-lKg",
      "text": "I'm serious now, This is the most unviewd vid from mrbeast",
      "likes": 1,
      "timestamp": 1640304000,
      "parent": "root",
      "is_reply": false
    },
    {
      "author": "@gokai961",
      "author_id": "UCvh2lGzzV1Pboe-4mzFMVmg",
      "text": "It feels extremely weird to see MrBeast the YouTuber who gets more then 10 million views on a average people having 12k views :/",
      "likes": 0,
      "timestamp": 1640304000,
      "parent": "root",
      "is_reply": false
    },
    {
      "author": "@yepijow4215",
      "author_id": "UCWT8dXv7vTk_lX2PsoTO_uA",
      "text": "493",
      "likes": 0,
      "timestamp": 1703376000,
      "parent": "root",
      "is_reply": false
    },
    {
      "author": "@yepijow4215",
      "author_id": "UCWT8dXv7vTk_lX2PsoTO_uA",
      "text": "491",
      "likes": 0,
      "timestamp": 1703376000,
      "parent": "root",
      "is_reply": false
    },
    {
      "author": "@HeartSoul98",
      "author_id": "UCr8JgsnFWjDG6Al8bMnTxfA",
      "text": "Im here looking for inspiration..to become a little famous to me..",
      "likes": 0,
      "timestamp": 1671840000,
      "parent": "root",
      "is_reply": false
    },
    {
      "author": "@ReconcilemE",
      "author_id": "UCNEJcIEJJH9lvFMsRaT8qiw",
      "text": "lmao this was good, next one should be 'hey want to play with me we would make a great youtube team, I am new to youtube but I am going to start a youtube channel lol",
      "likes": 16,
      "timestamp": 1450915200,
      "parent": "root",
      "is_reply": false
    },
    {
      "author": "@DoctorSoap_Sing",
      "author_id": "UCJfqbiXujLb-2goZ72h8PgA",
      "text": "307",
      "likes": 0,
      "timestamp": 1745452800,
      "parent": "root",
      "is_reply": false
    },
    {
      "author": "@yepijow4215",
      "author_id": "UCWT8dXv7vTk_lX2PsoTO_uA",
      "text": "478",
      "likes": 0,
      "timestamp": 1703376000,
      "parent": "root",
      "is_reply": false
    },
    {
      "author": "@yepijow4215",
      "author_id": "UCWT8dXv7vTk_lX2PsoTO_uA",
      "text": "498",
      "likes": 0,
      "timestamp": 1703376000,
      "parent": "root",
      "is_reply": false
    },
    {
      "author": "@ColinMartin-s7x",
      "author_id": "UCyKoBrmprbgrA8EqW0vUHiw",
      "text": "I’m the 516th to comment on a mrbeast vid",
      "likes": 0,
      "timestamp": 1764115200,
      "parent": "root",
      "is_reply": false
    },
    {
      "author": "@andrewburns-h3m",
      "author_id": "UCDWOXHIU-Sv5M2OIsI_Z-jQ",
      "text": "Last",
      "likes": 0,
      "timestamp": 1671840000,
      "parent": "root",
      "is_reply": false
    },
    {
      "author": "@connor_7198",
      "author_id": "UClrNLOj9bXJNttismNjSEDg",
      "text": "Yep, easy sub giveaways",
      "likes": 0,
      "timestamp": 1640304000,
      "parent": "root",
      "is_reply": false
    },
    {
      "author": "@yepijow4215",
      "author_id": "UCWT8dXv7vTk_lX2PsoTO_uA",
      "text": "495",
      "likes": 0,
      "timestamp": 1703376000,
      "parent": "root",
      "is_reply": false
    },
    {
      "author": "@yepijow4215",
      "author_id": "UCWT8dXv7vTk_lX2PsoTO_uA",
      "text": "If",
      "likes": 1,
      "timestamp": 1703376000,
      "parent": "root",
      "is_reply": false
    },
    {
      "author": "@yepijow4215",
      "author_id": "UCWT8dXv7vTk_lX2PsoTO_uA",
      "text": "496",
      "likes": 0,
      "timestamp": 1703376000,
      "parent": "root",
      "is_reply": false
    },
    {
      "author": "@TyvanTV",
      "author_id": "UCH2qly1u5B9_XtkdF6YAv-w",
      "text": "I want my shout so I can gain them 2 subs. PLAZ BEAST!",
      "likes": 0,
      "timestamp": 1608768000,
      "parent": "root",
      "is_reply": false
    },
    {
      "author": "@BraedenMartin",
      "author_id": "UCLQ5K-rmUvJPDqfqWTKUaRg",
      "text": "Wanna shoutout me",
      "likes": 0,
      "timestamp": 1577145600,
      "parent": "root",
      "is_reply": false
    },
    {
      "author": "@yepijow4215",
      "author_id": "UCWT8dXv7vTk_lX2PsoTO_uA",
      "text": "489",
      "likes": 0,
      "timestamp": 1703376000,
      "parent": "root",
      "is_reply": false
    },
    {
      "author": "@Grey_Slime",
      "author_id": "UCQn6y_0SoXoMlGB-a_bXecQ",
      "text": "И это самое не популярные видео mrbeast.😢",
      "likes": 0,
      "timestamp": 1734998400,
      "parent": "root",
      "is_reply": false
    },
    {
      "author": "@yepijow4215",
      "author_id": "UCWT8dXv7vTk_lX2PsoTO_uA",
      "text": "494",
      "likes": 0,
      "timestamp": 1703376000,
      "parent": "root",
      "is_reply": false
    },
    {
      "author": "@razvorot",
      "author_id": "UC6xYK2bbWuieJ2zuHP3OfOQ",
      "text": "Чо",
      "likes": 0,
      "timestamp": 1703376000,
      "parent": "root",
      "is_reply": false
    },
    {
      "author": "@montaserajlony",
      "author_id": "UCncpQxCiMCvSu32sxdL2x4w",
      "text": "Wow least viewd vid",
      "likes": 2,
      "timestamp": 1671840000,
      "parent": "root",
      "is_reply": false
    },
    {
      "author": "@yepijow4215",
      "author_id": "UCWT8dXv7vTk_lX2PsoTO_uA",
      "text": "you",
      "likes": 0,
      "timestamp": 1703376000,
      "parent": "root",
      "is_reply": false
    },
    {
      "author": "@yepijow4215",
      "author_id": "UCWT8dXv7vTk_lX2PsoTO_uA",
      "text": "486",
      "likes": 0,
      "timestamp": 1703376000,
      "parent": "root",
      "is_reply": false
    },
    {
      "author": "@yepijow4215",
      "author_id": "UCWT8dXv7vTk_lX2PsoTO_uA",
      "text": "485",
      "likes": 0,
      "timestamp": 1703376000,
      "parent": "root",
      "is_reply": false
    },
    {
      "author": "@yepijow4215",
      "author_id": "UCWT8dXv7vTk_lX2PsoTO_uA",
      "text": "488",
      "likes": 0,
      "timestamp": 1703376000,
      "parent": "root",
      "is_reply": false
    },
    {
      "author": "@BryanTheGamer",
      "author_id": "UCKH74Cj9pTxmOjrCvuc7XgA",
      "text": "Wtf ?",
      "likes": 1,
      "timestamp": 1450915200,
      "parent": "root",
      "is_reply": false
    },
    {
      "author": "@garrettcook7128",
      "author_id": "UCa4zD1sBe-o3HCQ-D2pu9Ig",
      "text": "Get good",
      "likes": 0,
      "timestamp": 1450915200,
      "parent": "root",
      "is_reply": false
    },
    {
      "author": "@yepijow4215",
      "author_id": "UCWT8dXv7vTk_lX2PsoTO_uA",
      "text": "499",
      "likes": 0,
      "timestamp": 1703376000,
      "parent": "root",
      "is_reply": false
    },
    {
      "author": "@돌아온용용이",
      "author_id": "UCSXu7sKO411DIhw4bQCtFPA",
      "text": "Mr. beast",
      "likes": 0,
      "timestamp": 1734998400,
      "parent": "root",
      "is_reply": false
    },
    {
      "author": "@Unknown-ex7yw",
      "author_id": "UCiXZM0WszYscnRkxy2lGIkQ",
      "text": "Mmm",
      "likes": 0,
      "timestamp": 1671840000,
      "parent": "root",
      "is_reply": false
    },
    {
      "author": "@fanboypotion4412",
      "author_id": "UCfTEr5LpkppRFINLcon38_w",
      "text": "Lmao only 279 comments. Pin?",
      "likes": 0,
      "timestamp": 1671840000,
      "parent": "root",
      "is_reply": false
    },
    {
      "author": "@Spuncer1",
      "author_id": "UCWz7AecuIdRHKsBCxe9aP-w",
      "text": "Hey can I have a shoutout on shoutout sunday",
      "likes": 0,
      "timestamp": 1671840000,
      "parent": "root",
      "is_reply": false
    },
    {
      "author": "@ExaktorYT",
      "author_id": "UCwOMnJfU9_EoUlm5uyAaZ4Q",
      "text": "I won the rock, paper, scissors for the first time. FINALLY I CAN UNSUB.\nJk. But keep up all the good work my man!",
      "likes": 19,
      "timestamp": 1450915200,
      "parent": "root",
      "is_reply": false
    },
    {
      "author": "@Mine_Stive_Bro",
      "author_id": "UCZLZe95IncbpnUjxgfWUshg",
      "text": "IM 797 who liked🤯🤯😱😱🙂🙂",
      "likes": 0,
      "timestamp": 1671840000,
      "parent": "root",
      "is_reply": false
    },
    {
      "author": "@jojoLeader",
      "author_id": "UCGAlyUeY9amNDrhh2VCkc5A",
      "text": "305번째 댓글입니다 지미!!!  언젠가 내댓글을 봐줬으면 좋겠어!  Challenge! My goal is to get a ❤ from you! :face-blue-smiling::face-blue-smiling::face-blue-smiling:",
      "likes": 0,
      "timestamp": 1703376000,
      "parent": "root",
      "is_reply": false
    },
    {
      "author": "@tylergordon6720",
      "author_id": "UCMMbBftNlFaJelOIKy0_kDw",
      "text": "8",
      "likes": 0,
      "timestamp": 1734998400,
      "parent": "root",
      "is_reply": false
    },
    {
      "author": "@jozahmann6147",
      "author_id": "UC7OwfTmOZ4JlNDnHLoNaqEw",
      "text": "ok i did all that stuff can i enter plz plz",
      "likes": 1,
      "timestamp": 1450915200,
      "parent": "root",
      "is_reply": false
    },
    {
      "author": "@CheeseboyYouTube",
      "author_id": "UCfBvZ_vFpvFnj-xiyEWAVyw",
      "text": "VT",
      "likes": 0,
      "timestamp": 1703376000,
      "parent": "root",
      "is_reply": false
    },
    {
      "author": "@Miroslaw987",
      "author_id": "UCgkyuSkZKCOFtp1kGh-8D8g",
      "text": "Hey beast,  how have you been?",
      "likes": 0,
      "timestamp": 1450915200,
      "parent": "root",
      "is_reply": false
    },
    {
      "author": "@Sherifskull369",
      "author_id": "UCAKCcaLk_3Z6NmMgLzEeRTQ",
      "text": "This has the least amount of views wow",
      "likes": 4,
      "timestamp": 1703376000,
      "parent": "root",
      "is_reply": false
    },
    {
      "author": "@orang_juic",
      "author_id": "UC3kZmajmIjGz0dr0P8fgJlA",
      "text": "I wasnt here",
      "likes": 0,
      "timestamp": 1703376000,
      "parent": "root",
      "is_reply": false
    },
    {
      "author": "@jeaberroya7531",
      "author_id": "UCLedWXq5G6m-GwnGs8kg5LQ",
      "text": "MRBEAST Notice Me!!!",
      "likes": 0,
      "timestamp": 1671840000,
      "parent": "root",
      "is_reply": false
    },
    {
      "author": "@trisman21323",
      "author_id": "UCdz03JKa4SRPx78-Y-ljpVw",
      "text": "Join my Shout out Sunday",
      "likes": 0,
      "timestamp": 1450915200,
      "parent": "root",
      "is_reply": false
    },
    {
      "author": "@skyl.12",
      "author_id": "UCJjC3BkQeIBaAYeTppGTZuQ",
      "text": ":v",
      "likes": 0,
      "timestamp": 1703376000,
      "parent": "root",
      "is_reply": false
    },
    {
      "author": "@shan_shan39",
      "author_id": "UCnzoBezstGRrMH0MTP8mKPw",
      "text": "うぇん",
      "likes": 0,
      "timestamp": 1703376000,
      "parent": "root",
      "is_reply": false
    },
    {
      "author": "@raeleengomez1203",
      "author_id": "UCMc2DISCVlbdHpmKUAdEr7w",
      "text": "I'll subscribe for 4 million dollars",
      "likes": 0,
      "timestamp": 1640304000,
      "parent": "root",
      "is_reply": false
    },
    {
      "author": "@sillymonkeyyy",
      "author_id": "UCum1hwny9Ky_jWhdbeRuAmQ",
      "text": "Damn 3 weeks since last comment",
      "likes": 0,
      "timestamp": 1734998400,
      "parent": "root",
      "is_reply": false
    },
    {
      "author": "@shaf730",
      "author_id": "UCyZKdyc8GvzcTFs9dZOKQRw",
      "text": "Comgrats to winners ✌️",
      "likes": 0,
      "timestamp": 1703376000,
      "parent": "root",
      "is_reply": false
    },
    {
      "author": "@hrickzonew8812",
      "author_id": "UCFZQaBOkCqnFhwDBPzogUOA",
      "text": "Ur lowest viewed vídeos dont go past 20k",
      "likes": 1,
      "timestamp": 1671840000,
      "parent": "root",
      "is_reply": false
    },
    {
      "author": "@phgames2704",
      "author_id": "UCq7bbxqXvoBafjHZCgfSPkw",
      "text": "Oi",
      "likes": 1,
      "timestamp": 1753315200,
      "parent": "root",
      "is_reply": false
    },
    {
      "author": "@apriciociricio8311",
      "author_id": "UC2lPd8t_5QtXkrMGrWYcFcw",
      "text": "Can u give me shout-out too",
      "likes": 0,
      "timestamp": 1671840000,
      "parent": "root",
      "is_reply": false
    },
    {
      "author": "@tikmotok9779",
      "author_id": "UChEawnrkfyeSAZB4RIXp3fQ",
      "text": "Give me a shoutout",
      "likes": 0,
      "timestamp": 1671840000,
      "parent": "root",
      "is_reply": false
    },
    {
      "author": "@matiBS-133",
      "author_id": "UCnPlg6CP4lXu3sJDYy7ZzmQ",
      "text": "2024?",
      "likes": 1,
      "timestamp": 1734998400,
      "parent": "root",
      "is_reply": false
    },
    {
      "author": "@satyamSaha",
      "author_id": "UCx2M2ovf2CVDUZeLtS9vmEQ",
      "text": "here before 30K",
      "likes": 0,
      "timestamp": 1703376000,
      "parent": "root",
      "is_reply": false
    },
    {
      "author": "@Jannatul89",
      "author_id": "UCNpZDZPX3lNiNZtIAMNImpg",
      "text": "So basically",
      "likes": 0,
      "timestamp": 1703376000,
      "parent": "root",
      "is_reply": false
    },
    {
      "author": "@jordanhippocrate4408",
      "author_id": "UCN9u-Pd3QUpZZMShBi9D7Aw",
      "text": ".",
      "likes": 0,
      "timestamp": 1671840000,
      "parent": "root",
      "is_reply": false
    },
    {
      "author": "@Jannatul89",
      "author_id": "UCNpZDZPX3lNiNZtIAMNImpg",
      "text": "So basically",
      "likes": 0,
      "timestamp": 1703376000,
      "parent": "root",
      "is_reply": false
    },
    {
      "author": "@CroissantCroissant-cz8ro",
      "author_id": "UChdVL-1EJ_aRdL-S4R4PdkQ",
      "text": "Pls pin",
      "likes": 0,
      "timestamp": 1703376000,
      "parent": "root",
      "is_reply": false
    },
    {
      "author": "@Reviolo",
      "author_id": "UCd4LlinNsAKrO5oENqpyWQQ",
      "text": "nice i could get 1-2 inactive subscribers. to bad i sold my soul for 3 views :(",
      "likes": 3,
      "timestamp": 1450915200,
      "parent": "root",
      "is_reply": false
    },
    {
      "author": "@Jannatul89",
      "author_id": "UCNpZDZPX3lNiNZtIAMNImpg",
      "text": "So basically",
      "likes": 0,
      "timestamp": 1703376000,
      "parent": "root",
      "is_reply": false
    },
    {
      "author": "@Jannatul89",
      "author_id": "UCNpZDZPX3lNiNZtIAMNImpg",
      "text": "So basically",
      "likes": 0,
      "timestamp": 1703376000,
      "parent": "root",
      "is_reply": false
    },
    {
      "author": "@Jannatul89",
      "author_id": "UCNpZDZPX3lNiNZtIAMNImpg",
      "text": "So basically",
      "likes": 0,
      "timestamp": 1703376000,
      "parent": "root",
      "is_reply": false
    },
    {
      "author": "@Jannatul89",
      "author_id": "UCNpZDZPX3lNiNZtIAMNImpg",
      "text": "So basically",
      "likes": 0,
      "timestamp": 1703376000,
      "parent": "root",
      "is_reply": false
    },
    {
      "author": "@Jannatul89",
      "author_id": "UCNpZDZPX3lNiNZtIAMNImpg",
      "text": "So basically",
      "likes": 0,
      "timestamp": 1703376000,
      "parent": "root",
      "is_reply": false
    },
    {
      "author": "@Jannatul89",
      "author_id": "UCNpZDZPX3lNiNZtIAMNImpg",
      "text": "So basically",
      "likes": 0,
      "timestamp": 1703376000,
      "parent": "root",
      "is_reply": false
    },
    {
      "author": "@Jannatul89",
      "author_id": "UCNpZDZPX3lNiNZtIAMNImpg",
      "text": "So basically",
      "likes": 0,
      "timestamp": 1703376000,
      "parent": "root",
      "is_reply": false
    },
    {
      "author": "@Jannatul89",
      "author_id": "UCNpZDZPX3lNiNZtIAMNImpg",
      "text": "So basically",
      "likes": 0,
      "timestamp": 1703376000,
      "parent": "root",
      "is_reply": false
    },
    {
      "author": "@gatien._",
      "author_id": "UCQBlA0m0JbplR-vto6on7YA",
      "text": "Que 30k vues ta flop",
      "likes": 0,
      "timestamp": 1703376000,
      "parent": "root",
      "is_reply": false
    },
    {
      "author": "@IntentionalFootball",
      "author_id": "UCRJoZFnPblRe1Yqk06Wz3KA",
      "text": "ignoring",
      "likes": 0,
      "timestamp": 1671840000,
      "parent": "root",
      "is_reply": false
    },
    {
      "author": "@Brendski",
      "author_id": "UCsYEU06h5xq04ngRQlkBUOg",
      "text": "Sell my soul? 0.0 do we have to do that part or were u just kidding?",
      "likes": 7,
      "timestamp": 1450915200,
      "parent": "root",
      "is_reply": false
    },
    {
      "author": "@ER2KYT",
      "author_id": "UCFMPw_Pq824QYArfs8ZCc8g",
      "text": "Amogus",
      "likes": 0,
      "timestamp": 1703376000,
      "parent": "root",
      "is_reply": false
    },
    {
      "author": "@Ibnesuaib.N",
      "author_id": "UCnw3EFmXg3VQjbRjV7Sld3Q",
      "text": "Love you brother ❤😢 contact me plz",
      "likes": 0,
      "timestamp": 1765324800,
      "parent": "root",
      "is_reply": false
    },
    {
      "author": "@lenaataei2278",
      "author_id": "UC6qhhwGutPvZbhzsIJ5ublg",
      "text": "U don't care about me?",
      "likes": 0,
      "timestamp": 1640304000,
      "parent": "root",
      "is_reply": false
    },
    {
      "author": "@Grayson-z8u",
      "author_id": "UCnNBHlJpgNTq19UJBSnOO8Q",
      "text": "Hey is this giveaway still opein?",
      "likes": 0,
      "timestamp": 1742774400,
      "parent": "root",
      "is_reply": false
    },
    {
      "author": "@R00k1e-1",
      "author_id": "UCE34Z5nf6-mOJjtbppY-SaQ",
      "text": "Anyone?",
      "likes": 0,
      "timestamp": 1761264000,
      "parent": "root",
      "is_reply": false
    },
    {
      "author": "@hermieromuar992",
      "author_id": "UC8gcqNP6oV2javqjEpnx9WQ",
      "text": "Lowest views",
      "likes": 2,
      "timestamp": 1703376000,
      "parent": "root",
      "is_reply": false
    },
    {
      "author": "@dreamxgeorgeuou886",
      "author_id": "UCIBevPjKRO2KsUzC2RxbPjw",
      "text": "P",
      "likes": 0,
      "timestamp": 1703376000,
      "parent": "root",
      "is_reply": false
    },
    {
      "author": "@thesparklingemerald",
      "author_id": "UCYN3iMJLzRYMn34RuIfsvQQ",
      "text": "So MrBeast is greedy\n\n\n\n\n\n   CASE CLOSED!!!",
      "likes": 0,
      "timestamp": 1577145600,
      "parent": "root",
      "is_reply": false
    },
    {
      "author": "@dovkornfeld7191",
      "author_id": "UCwx6uzzf8mwOQx27iDLRIkg",
      "text": "Anyone in 2024",
      "likes": 1,
      "timestamp": 1734998400,
      "parent": "root",
      "is_reply": false
    },
    {
      "author": "@sillysio3851",
      "author_id": "UCd5PzgZuvY9NmshBRfod7aw",
      "text": "Shout me out please",
      "likes": 0,
      "timestamp": 1671840000,
      "parent": "root",
      "is_reply": false
    },
    {
      "author": "@MoneyTimeKings",
      "author_id": "UC7PtUIwM7g81lZKEwd4vyqA",
      "text": "Yea shoutouts are pointless from all these small channels",
      "likes": 2,
      "timestamp": 1450915200,
      "parent": "root",
      "is_reply": false
    },
    {
      "author": "@gooseking6156",
      "author_id": "UCfisg35wt8sy8VbRvFnWSPA",
      "text": "LEAST VIEWED MR BEAST VIDEO LOL",
      "likes": 0,
      "timestamp": 1734998400,
      "parent": "root",
      "is_reply": false
    },
    {
      "author": "@joshuagifford3113",
      "author_id": "UCB5pawFLsuHGvy6TrwqwZoQ",
      "text": "Well hello there beast",
      "likes": 1,
      "timestamp": 1545609600,
      "parent": "root",
      "is_reply": false
    },
    {
      "author": "@ytcat497",
      "author_id": "UC8qTpauKVvg8pd1QZ9yVyiA",
      "text": "Yes timeworks bought me here",
      "likes": 4,
      "timestamp": 1703376000,
      "parent": "root",
      "is_reply": false
    },
    {
      "author": "@adolphusterry1076",
      "author_id": "UCjxTc4_zrTV1Nqd5JO14CiA",
      "text": "youwillpayforyourcrimes",
      "likes": 1,
      "timestamp": 1734998400,
      "parent": "root",
      "is_reply": false
    },
    {
      "author": "@derpy_dolphinz5375",
      "author_id": "UC00xe05fhmJOhumWv8Btcsg",
      "text": "Whos here in 2024? 👇",
      "likes": 1,
      "timestamp": 1734998400,
      "parent": "root",
      "is_reply": false
    },
    {
      "author": "@Kerim2134",
      "author_id": "UCYQU23JN9oo7mvrz20lZaSg",
      "text": "sa",
      "likes": 0,
      "timestamp": 1703376000,
      "parent": "root",
      "is_reply": false
    },
    {
      "author": "@ALPHANIMSwag",
      "author_id": "UCx94pkwsm9D6IDlkfApf9ag",
      "text": "IS THERE SOMEONE HERE? here here here",
      "likes": 4,
      "timestamp": 1734998400,
      "parent": "root",
      "is_reply": false
    },
    {
      "author": "@Nathankassab",
      "author_id": "UC5fH_QvlfEa5bQNk243h08A",
      "text": "Most unviewed mrbeast vid",
      "likes": 2,
      "timestamp": 1671840000,
      "parent": "root",
      "is_reply": false
    },
    {
      "author": "@Landon693",
      "author_id": "UCaITqDU9GH5xo8y-4F3uoJw",
      "text": "Who else went to popular and scrolled all the way down",
      "likes": 2,
      "timestamp": 1703376000,
      "parent": "root",
      "is_reply": false
    },
    {
      "author": "@charlidamelio890",
      "author_id": "UCuoVjzj915YJ3IzYGpLYWbA",
      "text": "Mr beast.......",
      "likes": 0,
      "timestamp": 1640304000,
      "parent": "root",
      "is_reply": false
    }
  ],
  "error": null
}